Workbook
Name MODO_DEMO: '01_CONTROL_PANEL'!$C$7
Name KG_SACO_STD: '01_CONTROL_PANEL'!$C$9
Name SACO_PALETE_STD: '01_CONTROL_PANEL'!$C$10
Name KG_SACO_EXT: '01_CONTROL_PANEL'!$C$11
Name SACO_PALETE_EXT: '01_CONTROL_PANEL'!$C$12
Name KG_PALETE: '01_CONTROL_PANEL'!$C$13
Name CONCHA_M3: '01_CONTROL_PANEL'!$C$14
Name ICMS_NOMINAL: '01_CONTROL_PANEL'!$C$16
Name ICMS_REDUCAO: '01_CONTROL_PANEL'!$C$17
Name ICMS_PCT_DEVIDO: '01_CONTROL_PANEL'!$C$18
Name ICMS_EFETIVO: '01_CONTROL_PANEL'!$C$19
Name PIS_DEBITO: '01_CONTROL_PANEL'!$C$21
Name COFINS_DEBITO: '01_CONTROL_PANEL'!$C$22
Name IRPJ_ALIQ: '01_CONTROL_PANEL'!$C$24
Name IRPJ_ADIC: '01_CONTROL_PANEL'!$C$25
Name CSLL_ALIQ: '01_CONTROL_PANEL'!$C$26
Name SUDENE_REDUCAO: '01_CONTROL_PANEL'!$C$27
Name CUSTO_CAPITAL_ANO: '01_CONTROL_PANEL'!$C$29
Name INADIMPL_PCT: '01_CONTROL_PANEL'!$C$30
Name DIAS_ANO: '01_CONTROL_PANEL'!$C$31
Name MAT_CLASSE_A: '01_CONTROL_PANEL'!$C$33
Name MAT_CLASSE_B: '01_CONTROL_PANEL'!$C$34
Name VOLUME_ANO_T: '01_CONTROL_PANEL'!$C$35

Sheet 00_README
A1: SKAL INDUSTRIAL COST INTELLIGENCE SYSTEM
A2: Digital Cost Twin da operacao industrial — Grupo Kalfix / SKAL. Gerado por build_skal_cost_system.py (fonte da verdade da estrutura).
B4: O QUE E | C4: Sistema modular e auditavel que responde, para qualquer SKU: quanto custou, quanto deveria ter custado, quanto custaria hoje, qual o desvio, onde/porque ocorreu, quanto e controlavel, e quanto vale elimina-lo.
B5: CINCO FUNCOES | C5: 1) Cost Accounting (quanto custou) 2) Cost Engineering (quanto deveria) 3) Cost Control (onde desviou) 4) Cost Reduction (quanto economizar) 5) Profitability Intelligence (onde ganha/perde dinheiro).
B6: COMO USAR | C6: Preencha as celulas AMARELAS (INPUT). Celulas brancas sao FORMULA; azuis sao dados de outra aba (LINKED); verdes sao CONTROL; vermelhas sao ALERT. Nao altere formulas estruturais. Premissas globais ficam em 01_CONTROL_PANEL.
B7: MODO DEMO | C7: 01_CONTROL_PANEL!MODO_DEMO liga um pequeno dataset de DEMONSTRACAO (marcado em cada linha) que permite os testes matematicos. Numeros DEMO NAO sao dados reais da SKAL — veja DATA_GAPS para o que precisa ser preenchido.
B8: RECONCILIACAO | C8: Regra central: Standard Cost + Variances (PPV+Uso+Mix+Yield) = Actual Cost, residual -> 0. BOM fecha fisicamente. Nenhum custo e rateado sem driver causal (vai para UNALLOCATED).
B10: DICIONARIO DE INDICADORES-CHAVE
B11: Indicador | C11: Definicao / Formula | D11: Unidade | E11: Resp.
B12: Landed Net Cost | C12: Bruto - descontos - creditos recup. + frete/seguro/descarga + trib. nao recup. | D12: R$/t | E12: Compras/Fiscal
B13: Material Cost / Good Ton | C13: Custo total materiais consumidos / toneladas boas liberadas | D13: R$/t | E13: Producao/Contr.
B14: PPV | C14: (Preco real - preco padrao) x quantidade real | D14: R$ | E14: Compras
B15: Usage Variance | C15: (Qtd real - qtd padrao permitida) x preco padrao | D15: R$ | E15: Producao
B16: Mix Variance | C16: Efeito da alteracao da composicao relativa da formula (sub-split do uso) | D16: R$ | E16: Tecnico
B17: Yield Variance | C17: (Output bom esperado - obtido) valorizado ao custo padrao | D17: R$ | E17: Producao
B18: Unused Capacity Cost | C18: Horas ociosas x custo/hora de capacidade pratica (NAO rateado ao produto) | D18: R$ | E18: Controladoria
B19: COPQ | C19: Custo da ma qualidade: scrap+reprocesso+retrabalho+devolucao+frete reverso... | D19: R$ | E19: Qualidade
B20: Cost Gap | C20: Actual -> Current Std -> Best Demonstrated -> Entitlement -> Teorico | D20: R$/t | E20: Controladoria
B21: Pocket Price | C21: Preco tabela - descontos - bonif - rebate - comissao - frete - custo prazo - inadimpl. | D21: R$ | E21: Comercial
B22: Pocket Margin | C22: Pocket Price - custo reposicao - cost to serve - tributacao economica | D22: R$ | E22: Comercial/Contr.
... B24: Saving Realizado | C24: Saving com evidencia operacional + confirmacao financeira + reconciliacao | D24: R$ | E24: Controladoria
B26: INDICE DE ABAS
B27: Aba | C27: Grupo | D27: Proposito
B28: 00_README | C28: Doc | D28: Documentacao, metodologia e indice
B29: 01_CONTROL_PANEL | C29: Core | D29: Premissas globais parametrizadas
B30: 02_CALENDAR | C30: Core | D30: Periodos e vigencias
B31: 03_PRODUCTS | C31: Master Data | D31: Cadastro de produtos (SKU)
B32: 04_MATERIALS | C32: Master Data | D32: Cadastro de materias-primas
B33: 05_SUPPLIERS | C33: Master Data | D33: Cadastro de fornecedores
B34: 06_BOM | C34: Engineering | D34: Formulacao tecnica e economica (BOM)
B35: 07_BOM_VERSION | C35: Engineering | D35: Controle de versoes de formulacao
B36: 09_LANDED_COST | C36: Procurement | D36: Custo liquido posto fabrica
B37: 10_TAX_RULES | C37: Tax | D37: Motor tributario (regras por vigencia)
B38: 11_TAX_CREDITS | C38: Tax | D38: Creditos tributarios (potencial->monetizado)
... B86: R5_FRETES_CTE | C86: Real | D86: Fretes inbound (CT-e)

Sheet 01_CONTROL_PANEL
A1: PAINEL DE CONTROLE — PREMISSAS GLOBAIS
A2: Toda premissa critica vive aqui e e referenciada por NOME. Nenhuma aliquota digitada dentro de formula. Edite apenas a coluna VALOR (amarela).
A4: Legenda: | B4: INPUT (editavel) | D4: FORMULA | F4: LINKED (de outra aba) | H4: CONTROL | J4: ALERT | L4: CHAVE/ID
A6: # | B6: Parametro | C6: Valor | D6: Un. | E6: Descricao / regra | F6: Fonte | G6: Responsavel
A7: MODO_DEMO | B7: Modo demonstracao (TRUE/FALSE) | C7: TRUE | D7: - | E7: TRUE liga dataset DEMO p/ testes; FALSE zera exemplos | F7: Controladoria | G7: Controller
B8: — CONVERSOES DE EMBALAGEM —
A9: KG_SACO_STD | B9: kg por saco (padrao) | C9: 15 | D9: kg | E9: Linhas gerais SKAL | F9: Producao | G9: Sup. Prod.
A10: SACO_PALETE_STD | B10: sacos por palete (padrao) | C10: 100 | D10: un | E10: Linhas gerais | F10: Producao | G10: Sup. Prod.
A11: KG_SACO_EXT | B11: kg por saco (linha Extras) | C11: 20 | D11: kg | E11: Multiuso/Graute/Reboco/Contrapiso | F11: Producao | G11: Sup. Prod.
A12: SACO_PALETE_EXT | B12: sacos por palete (Extras) | C12: 75 | D12: un | E12: Linha Extras | F12: Producao | G12: Sup. Prod.
A13: KG_PALETE | B13: kg por palete (todas) | C13: 1500 | D13: kg | E13: 1.500 kg/palete em ambas as linhas | F13: Producao | G13: Sup. Prod.
A14: CONCHA_M3 | B14: m3 por concha (Komatsu WA200-5) | C14: 2.1 | D14: m3 | E14: Elo com Painel do Forno (areia) | F14: Producao | G14: Sup. Prod.
B15: — ICMS (beneficio 80%) —
A16: ICMS_NOMINAL | B16: ICMS aliquota nominal | C16: 0.225 | D16: % | E16: Aliquota cheia | F16: Fiscal | G16: Cont. Fiscal
A17: ICMS_REDUCAO | B17: ICMS reducao do beneficio | C17: 0.8 | D17: % | E17: Reducao de 80% do ICMS devido | F17: Fiscal | G17: Cont. Fiscal
A18: ICMS_PCT_DEVIDO | B18: ICMS % efetivamente devido | C18: =1-ICMS_REDUCAO | D18: % | E18: 1 menos reducao (da 20%) | F18: Fiscal | G18: Cont. Fiscal
A19: ICMS_EFETIVO | B19: ICMS efetivo (calc.) | C19: =ICMS_NOMINAL*ICMS_PCT_DEVIDO | D19: % | E19: nominal x %devido (=4,5%) NUNCA hardcoded | F19: Fiscal | G19: Cont. Fiscal
B20: — PIS/COFINS (Lucro Real, nao cumulativo) —
A21: PIS_DEBITO | B21: PIS debito | C21: 0.0165 | D21: % | E21: Nao cumulativo | F21: Fiscal | G21: Cont. Fiscal
A22: COFINS_DEBITO | B22: COFINS debito | C22: 0.076 | D22: % | E22: Nao cumulativo (soma 9,25%) | F22: Fiscal | G22: Cont. Fiscal
B23: — IRPJ / CSLL / SUDENE —
A24: IRPJ_ALIQ | B24: IRPJ aliquota | C24: 0.15 | D24: % | E24: 15% + adicional | F24: Fiscal | G24: Cont. Fiscal
A25: IRPJ_ADIC | B25: IRPJ adicional (>20k/mes) | C25: 0.1 | D25: % | E25: 10% sobre excedente | F25: Fiscal | G25: Cont. Fiscal
A26: CSLL_ALIQ | B26: CSLL aliquota | C26: 0.09 | D26: % | E26: NUNCA aplicar reducao SUDENE a CSLL | F26: Fiscal | G26: Cont. Fiscal
A27: SUDENE_REDUCAO | B27: SUDENE reducao IRPJ elegivel | C27: 0.75 | D27: % | E27: 75% do IRPJ elegivel (parametrizavel) | F27: Fiscal | G27: Diretoria
B28: — FINANCEIRO —
A29: CUSTO_CAPITAL_ANO | B29: Custo de capital anual | C29: 0.18 | D29: % | E29: Para custo de prazo e estoque (DEMO) | F29: Financeiro | G29: CFO
A30: INADIMPL_PCT | B30: Inadimplencia esperada (%) | C30: 0.015 | D30: % | E30: Taxa historica parametrizada (DEMO) | F30: Financeiro | G30: Credito
A31: DIAS_ANO | B31: Dias no ano (base financeira) | C31: 365 | D31: d | E31: Base p/ custo de prazo | F31: Financeiro | G31: CFO
B32: — MATERIALIDADE / GOVERNANCA —
A33: MAT_CLASSE_A | B33: Materialidade Classe A (R$/ano) | C33: 100000 | D33: R$ | E33: Impacto alto | F33: Controladoria | G33: Controller
A34: MAT_CLASSE_B | B34: Materialidade Classe B (R$/ano) | C34: 25000 | D34: R$ | E34: Impacto medio | F34: Controladoria | G34: Controller
A35: VOLUME_ANO_T | B35: Volume anual referencia (t) | C35: 70000 | D35: t | E35: Para anualizar gaps (DEMO) | F35: Comercial | G35: Diretoria

Sheet 02_CALENDAR
A1: CALENDAR
A2: Controle temporal. A reforma tributaria e tratada por DATA DE VIGENCIA (ver 10_TAX_RULES), nunca sobrescrevendo regra antiga.
A4: Legenda: | B4: INPUT (editavel) | D4: FORMULA | F4: LINKED (de outra aba) | H4: CONTROL | J4: ALERT | L4: CHAVE/ID
A6: PERIOD_ID | B6: Ano | C6: Mes | D6: Data ini | E6: Data fim | F6: Dias uteis | G6: Regime tributario vigente | H6: Status
A7: 2026-01 | B7: 2026 | C7: 1 | D7: 2026-01-01 | E7: 2026-01-31 | F7: 22 | G7: ICMS benef. 80% + PIS/COFINS n-cum | H7: Fechado
A8: 2026-02 | B8: 2026 | C8: 2 | D8: 2026-02-01 | E8: 2026-02-28 | F8: 20 | G8: ICMS benef. 80% + PIS/COFINS n-cum | H8: Fechado
A9: 2026-03 | B9: 2026 | C9: 3 | D9: 2026-03-01 | E9: 2026-03-31 | F9: 21 | G9: ICMS benef. 80% + PIS/COFINS n-cum | H9: Aberto
A11: ^ Linhas acima = dados DEMO (marcados). Abaixo: campos de entrada em branco para dados reais.

Sheet 03_PRODUCTS
A1: PRODUCTS
A2: Conversoes de embalagem automaticas. Excecao linha Extras (Multiuso/Graute/Reboco/Contrapiso): 20 kg/saco, 75 sacos/palete.
A4: Legenda: | B4: INPUT (editavel) | D4: FORMULA | F4: LINKED (de outra aba) | H4: CONTROL | J4: ALERT | L4: CHAVE/ID
A6: PRODUCT_ID | B6: Descricao | C6: Familia | D6: Linha | E6: Unid. comercial | F6: Extras? | G6: kg/saco | H6: sacos/ palete | I6: kg/palete | J6: FORMULA_ID | K6: Versao | L6: ROUTING_ID | M6: RESOURCE principal | N6: Familia setup | O6: NCM | P6: Unid. industrial | Q6: Status | R6: Vigencia ini | S6: Vigencia fim
A7: P001 | B7: Multiuso | C7: Extras | D7: Extras | E7: saco | F7: TRUE | G7: =IF(F7,KG_SACO_EXT,KG_SACO_STD) | H7: =IF(F7,SACO_PALETE_EXT,SACO_PALETE_STD) | I7: =G7*H7 | J7: F-P001 | K7: v1 | L7: RT-EXT | M7: RES-MIST1 | N7: Extras | O7: 3824.50.00 | P7: t | Q7: Ativo | R7: 2026-01-01
A8: P002 | B8: Argamassa Assentamento AC-III | C8: Assentamento | D8: Colante | E8: saco | F8: FALSE | G8: =IF(F8,KG_SACO_EXT,KG_SACO_STD) | H8: =IF(F8,SACO_PALETE_EXT,SACO_PALETE_STD) | I8: =G8*H8 | J8: F-P002 | K8: v1 | L8: RT-ARG | M8: RES-MIST1 | N8: Colante | O8: 3824.50.00 | P8: t | Q8: Ativo | R8: 2026-01-01
A9: P003 | B9: Rejunte | C9: Rejunte | D9: Rejunte | E9: saco | F9: FALSE | G9: =IF(F9,KG_SACO_EXT,KG_SACO_STD) | H9: =IF(F9,SACO_PALETE_EXT,SACO_PALETE_STD) | I9: =G9*H9 | J9: F-P003 | K9: v1 | L9: RT-REJ | M9: RES-MIST2 | N9: Rejunte | O9: 3824.50.00 | P9: t | Q9: Ativo | R9: 2026-01-01
G10: =IF($F10=TRUE,KG_SACO_EXT,KG_SACO_STD) | H10: =IF($F10=TRUE,SACO_PALETE_EXT,SACO_PALETE_STD) | I10: =G10*H10
G11: =IF($F11=TRUE,KG_SACO_EXT,KG_SACO_STD) | H11: =IF($F11=TRUE,SACO_PALETE_EXT,SACO_PALETE_STD) | I11: =G11*H11
G12: =IF($F12=TRUE,KG_SACO_EXT,KG_SACO_STD) | H12: =IF($F12=TRUE,SACO_PALETE_EXT,SACO_PALETE_STD) | I12: =G12*H12
G13: =IF($F13=TRUE,KG_SACO_EXT,KG_SACO_STD) | H13: =IF($F13=TRUE,SACO_PALETE_EXT,SACO_PALETE_STD) | I13: =G13*H13
G14: =IF($F14=TRUE,KG_SACO_EXT,KG_SACO_STD) | H14: =IF($F14=TRUE,SACO_PALETE_EXT,SACO_PALETE_STD) | I14: =G14*H14
G15: =IF($F15=TRUE,KG_SACO_EXT,KG_SACO_STD) | H15: =IF($F15=TRUE,SACO_PALETE_EXT,SACO_PALETE_STD) | I15: =G15*H15
G16: =IF($F16=TRUE,KG_SACO_EXT,KG_SACO_STD) | H16: =IF($F16=TRUE,SACO_PALETE_EXT,SACO_PALETE_STD) | I16: =G16*H16
G17: =IF($F17=TRUE,KG_SACO_EXT,KG_SACO_STD) | H17: =IF($F17=TRUE,SACO_PALETE_EXT,SACO_PALETE_STD) | I17: =G17*H17
G18: =IF($F18=TRUE,KG_SACO_EXT,KG_SACO_STD) | H18: =IF($F18=TRUE,SACO_PALETE_EXT,SACO_PALETE_STD) | I18: =G18*H18
G19: =IF($F19=TRUE,KG_SACO_EXT,KG_SACO_STD) | H19: =IF($F19=TRUE,SACO_PALETE_EXT,SACO_PALETE_STD) | I19: =G19*H19
G20: =IF($F20=TRUE,KG_SACO_EXT,KG_SACO_STD) | H20: =IF($F20=TRUE,SACO_PALETE_EXT,SACO_PALETE_STD) | I20: =G20*H20
G21: =IF($F21=TRUE,KG_SACO_EXT,KG_SACO_STD) | H21: =IF($F21=TRUE,SACO_PALETE_EXT,SACO_PALETE_STD) | I21: =G21*H21
... G46: =IF($F46=TRUE,KG_SACO_EXT,KG_SACO_STD) | H46: =IF($F46=TRUE,SACO_PALETE_EXT,SACO_PALETE_STD) | I46: =G46*H46

Sheet 04_MATERIALS
A1: MATERIALS
A2: Cada MP tem chave unica, funcao tecnica e substituto. Recuperabilidade tributaria alimenta o Landed Net Cost.
A4: Legenda: | B4: INPUT (editavel) | D4: FORMULA | F4: LINKED (de outra aba) | H4: CONTROL | J4: ALERT | L4: CHAVE/ID
A6: MATERIAL_ID | B6: Descricao | C6: Grupo | D6: Unid. | E6: NCM | F6: Funcao tecnica | G6: Substituto (MATERIAL_ID) | H6: Recuperavel ICMS? | I6: Recuperavel PIS/COFINS? | J6: Classe (A/B/C) | K6: Fonte | L6: Responsavel | M6: Vigencia ini | N6: Vigencia fim | O6: Atualizado em | P6: Comentario
A7: M001 | B7: Cimento CP-II-32 | C7: Aglomerante | D7: t | E7: 2523.29.10 | F7: Aglomerante estrutural | H7: Sim | I7: Sim | J7: A
A8: M002 | B8: Areia industrial seca | C8: Agregado | D8: t | E8: 2505.10.00 | F8: Agregado/carga | H8: Sim | I8: Sim | J8: A
A9: M003 | B9: Cal hidratada CH-I | C9: Aglomerante | D9: t | E9: 2522.20.00 | F9: Plastificante/retencao | H9: Sim | I9: Sim | J9: B
A10: M004 | B10: Aditivo retentor de agua (HEC) | C10: Aditivo | D10: kg | E10: 3912.39.00 | F10: Retencao de agua/trabalhab. | H10: Sim | I10: Sim | J10: B
A11: M005 | B11: Pigmento oxido de ferro | C11: Aditivo | D11: kg | E11: 2821.10.00 | F11: Coloracao | H11: Sim | I11: Sim | J11: C
A13: ^ Linhas acima = dados DEMO (marcados). Abaixo: campos de entrada em branco para dados reais.

Sheet 05_SUPPLIERS
A1: SUPPLIERS
A2: Base para Landed Cost, Supplier TCO e Should Cost.
A4: Legenda: | B4: INPUT (editavel) | D4: FORMULA | F4: LINKED (de outra aba) | H4: CONTROL | J4: ALERT | L4: CHAVE/ID
A6: SUPPLIER_ID | B6: Razao social | C6: UF | D6: Fornece (grupo) | E6: Lead time (d) | F6: Lote min (t) | G6: Condicao pgto (d) | H6: Rating qualidade | I6: Estrategico? | J6: Fonte | K6: Responsavel | L6: Vigencia ini | M6: Vigencia fim | N6: Atualizado em | O6: Comentario
A7: S001 | B7: Cimento Fornecedor A | C7: CE | D7: Cimento | E7: 3 | F7: 27 | G7: 28 | H7: A | I7: Sim
A8: S002 | B8: Mineracao Areia (ASSIS/SKAL) | C8: CE | D8: Areia | E8: 2 | F8: 30 | G8: 21 | H8: B | I8: Sim
A9: S003 | B9: Quimica Aditivos B | C9: SP | D9: Aditivo/Pigmento | E9: 10 | F9: 1 | G9: 30 | H9: A | I9: Nao
A11: ^ Linhas acima = dados DEMO (marcados). Abaixo: campos de entrada em branco para dados reais.

Sheet 06_BOM
A1: BOM
A2: kg/t x LANDED NET R$/t = custo padrao de material. Soma de kg/t deve fechar com o peso tecnico (1.000 kg/t). Alerta se nao fechar.
A4: Legenda: | B4: INPUT (editavel) | D4: FORMULA | F4: LINKED (de outra aba) | H4: CONTROL | J4: ALERT | L4: CHAVE/ID
A6: PRODUCT_ID | B6: FORMULA_ID | C6: Versao | D6: MATERIAL_ID | E6: kg / t produto | F6: % massa | G6: Min kg/t | H6: Max kg/t | I6: Funcao tecnica | J6: Substituto | K6: LANDED R$/t (link) | L6: Custo padrao R$/t produto | M6: KEY (prod|mat)
A7: P001 | B7: F-P001 | C7: v1 | D7: M001 | E7: 250 | F7: =E7/1000 | I7: Aglomerante | K7: =IFERROR(INDEX('09_LANDED_COST'!$P$7:$P$47,MATCH(D7,'09_LANDED_COST'!$A$7:$A$47,0)),0) | L7: =E7/1000*K7 | M7: =A7&"|"&D7
A8: P001 | B8: F-P001 | C8: v1 | D8: M002 | E8: 700 | F8: =E8/1000 | I8: Agregado | K8: =IFERROR(INDEX('09_LANDED_COST'!$P$7:$P$47,MATCH(D8,'09_LANDED_COST'!$A$7:$A$47,0)),0) | L8: =E8/1000*K8 | M8: =A8&"|"&D8
A9: P001 | B9: F-P001 | C9: v1 | D9: M003 | E9: 45 | F9: =E9/1000 | I9: Plastificante | K9: =IFERROR(INDEX('09_LANDED_COST'!$P$7:$P$47,MATCH(D9,'09_LANDED_COST'!$A$7:$A$47,0)),0) | L9: =E9/1000*K9 | M9: =A9&"|"&D9
A10: P001 | B10: F-P001 | C10: v1 | D10: M004 | E10: 5 | F10: =E10/1000 | I10: Retentor agua | K10: =IFERROR(INDEX('09_LANDED_COST'!$P$7:$P$47,MATCH(D10,'09_LANDED_COST'!$A$7:$A$47,0)),0) | L10: =E10/1000*K10 | M10: =A10&"|"&D10
A11: P002 | B11: F-P002 | C11: v1 | D11: M001 | E11: 300 | F11: =E11/1000 | I11: Aglomerante | K11: =IFERROR(INDEX('09_LANDED_COST'!$P$7:$P$47,MATCH(D11,'09_LANDED_COST'!$A$7:$A$47,0)),0) | L11: =E11/1000*K11 | M11: =A11&"|"&D11
A12: P002 | B12: F-P002 | C12: v1 | D12: M002 | E12: 650 | F12: =E12/1000 | I12: Agregado | K12: =IFERROR(INDEX('09_LANDED_COST'!$P$7:$P$47,MATCH(D12,'09_LANDED_COST'!$A$7:$A$47,0)),0) | L12: =E12/1000*K12 | M12: =A12&"|"&D12
A13: P002 | B13: F-P002 | C13: v1 | D13: M003 | E13: 45 | F13: =E13/1000 | I13: Plastificante | K13: =IFERROR(INDEX('09_LANDED_COST'!$P$7:$P$47,MATCH(D13,'09_LANDED_COST'!$A$7:$A$47,0)),0) | L13: =E13/1000*K13 | M13: =A13&"|"&D13
A14: P002 | B14: F-P002 | C14: v1 | D14: M004 | E14: 5 | F14: =E14/1000 | I14: Retentor agua | K14: =IFERROR(INDEX('09_LANDED_COST'!$P$7:$P$47,MATCH(D14,'09_LANDED_COST'!$A$7:$A$47,0)),0) | L14: =E14/1000*K14 | M14: =A14&"|"&D14
A15: P003 | B15: F-P003 | C15: v1 | D15: M001 | E15: 350 | F15: =E15/1000 | I15: Aglomerante | K15: =IFERROR(INDEX('09_LANDED_COST'!$P$7:$P$47,MATCH(D15,'09_LANDED_COST'!$A$7:$A$47,0)),0) | L15: =E15/1000*K15 | M15: =A15&"|"&D15
A16: P003 | B16: F-P003 | C16: v1 | D16: M002 | E16: 600 | F16: =E16/1000 | I16: Agregado | K16: =IFERROR(INDEX('09_LANDED_COST'!$P$7:$P$47,MATCH(D16,'09_LANDED_COST'!$A$7:$A$47,0)),0) | L16: =E16/1000*K16 | M16: =A16&"|"&D16
A17: P003 | B17: F-P003 | C17: v1 | D17: M004 | E17: 8 | F17: =E17/1000 | I17: Retentor agua | K17: =IFERROR(INDEX('09_LANDED_COST'!$P$7:$P$47,MATCH(D17,'09_LANDED_COST'!$A$7:$A$47,0)),0) | L17: =E17/1000*K17 | M17: =A17&"|"&D17
A18: P003 | B18: F-P003 | C18: v1 | D18: M005 | E18: 42 | F18: =E18/1000 | I18: Pigmento | K18: =IFERROR(INDEX('09_LANDED_COST'!$P$7:$P$47,MATCH(D18,'09_LANDED_COST'!$A$7:$A$47,0)),0) | L18: =E18/1000*K18 | M18: =A18&"|"&D18
F19: =IF(E19="","",E19/1000) | K19: =IF(D19="","",IFERROR(INDEX('09_LANDED_COST'!$P$7:$P$47,MATCH(D19,'09_LANDED_COST'!$A$7:$A$47,0)),0)) | L19: =IF(E19="","",E19/1000*K19) | M19: =IF(A19="","",A19&"|"&D19)
F20: =IF(E20="","",E20/1000) | K20: =IF(D20="","",IFERROR(INDEX('09_LANDED_COST'!$P$7:$P$47,MATCH(D20,'09_LANDED_COST'!$A$7:$A$47,0)),0)) | L20: =IF(E20="","",E20/1000*K20) | M20: =IF(A20="","",A20&"|"&D20)
F21: =IF(E21="","",E21/1000) | K21: =IF(D21="","",IFERROR(INDEX('09_LANDED_COST'!$P$7:$P$47,MATCH(D21,'09_LANDED_COST'!$A$7:$A$47,0)),0)) | L21: =IF(E21="","",E21/1000*K21) | M21: =IF(A21="","",A21&"|"&D21)
F22: =IF(E22="","",E22/1000) | K22: =IF(D22="","",IFERROR(INDEX('09_LANDED_COST'!$P$7:$P$47,MATCH(D22,'09_LANDED_COST'!$A$7:$A$47,0)),0)) | L22: =IF(E22="","",E22/1000*K22) | M22: =IF(A22="","",A22&"|"&D22)
F23: =IF(E23="","",E23/1000) | K23: =IF(D23="","",IFERROR(INDEX('09_LANDED_COST'!$P$7:$P$47,MATCH(D23,'09_LANDED_COST'!$A$7:$A$47,0)),0)) | L23: =IF(E23="","",E23/1000*K23) | M23: =IF(A23="","",A23&"|"&D23)
F24: =IF(E24="","",E24/1000) | K24: =IF(D24="","",IFERROR(INDEX('09_LANDED_COST'!$P$7:$P$47,MATCH(D24,'09_LANDED_COST'!$A$7:$A$47,0)),0)) | L24: =IF(E24="","",E24/1000*K24) | M24: =IF(A24="","",A24&"|"&D24)
F25: =IF(E25="","",E25/1000) | K25: =IF(D25="","",IFERROR(INDEX('09_LANDED_COST'!$P$7:$P$47,MATCH(D25,'09_LANDED_COST'!$A$7:$A$47,0)),0)) | L25: =IF(E25="","",E25/1000*K25) | M25: =IF(A25="","",A25&"|"&D25)
F26: =IF(E26="","",E26/1000) | K26: =IF(D26="","",IFERROR(INDEX('09_LANDED_COST'!$P$7:$P$47,MATCH(D26,'09_LANDED_COST'!$A$7:$A$47,0)),0)) | L26: =IF(E26="","",E26/1000*K26) | M26: =IF(A26="","",A26&"|"&D26)
F27: =IF(E27="","",E27/1000) | K27: =IF(D27="","",IFERROR(INDEX('09_LANDED_COST'!$P$7:$P$47,MATCH(D27,'09_LANDED_COST'!$A$7:$A$47,0)),0)) | L27: =IF(E27="","",E27/1000*K27) | M27: =IF(A27="","",A27&"|"&D27)
F28: =IF(E28="","",E28/1000) | K28: =IF(D28="","",IFERROR(INDEX('09_LANDED_COST'!$P$7:$P$47,MATCH(D28,'09_LANDED_COST'!$A$7:$A$47,0)),0)) | L28: =IF(E28="","",E28/1000*K28) | M28: =IF(A28="","",A28&"|"&D28)
F29: =IF(E29="","",E29/1000) | K29: =IF(D29="","",IFERROR(INDEX('09_LANDED_COST'!$P$7:$P$47,MATCH(D29,'09_LANDED_COST'!$A$7:$A$47,0)),0)) | L29: =IF(E29="","",E29/1000*K29) | M29: =IF(A29="","",A29&"|"&D29)
F30: =IF(E30="","",E30/1000) | K30: =IF(D30="","",IFERROR(INDEX('09_LANDED_COST'!$P$7:$P$47,MATCH(D30,'09_LANDED_COST'!$A$7:$A$47,0)),0)) | L30: =IF(E30="","",E30/1000*K30) | M30: =IF(A30="","",A30&"|"&D30)
... F66: =IF(E66="","",E66/1000) | K66: =IF(D66="","",IFERROR(INDEX('09_LANDED_COST'!$P$7:$P$47,MATCH(D66,'09_LANDED_COST'!$A$7:$A$47,0)),0)) | L66: =IF(E66="","",E66/1000*K66) | M66: =IF(A66="","",A66&"|"&D66)
A69: CONTROLE — FECHAMENTO DA FORMULACAO (peso tecnico)
A70: PRODUCT_ID | B70: Soma kg/t | C70: Peso alvo | D70: Fecha? | E70: Custo padrao MATERIAL R$/t
A71: P001 | B71: =SUMIF($A$7:$A$67,A71,$E$7:$E$67) | C71: =KG_PALETE/ (KG_PALETE/1000) | D71: =IF(ABS(B71-1000)<=1,"OK","VERIFICAR") | E71: =SUMIF($A$7:$A$67,A71,$L$7:$L$67)
A72: P002 | B72: =SUMIF($A$7:$A$67,A72,$E$7:$E$67) | C72: =KG_PALETE/ (KG_PALETE/1000) | D72: =IF(ABS(B72-1000)<=1,"OK","VERIFICAR") | E72: =SUMIF($A$7:$A$67,A72,$L$7:$L$67)
A73: P003 | B73: =SUMIF($A$7:$A$67,A73,$E$7:$E$67) | C73: =KG_PALETE/ (KG_PALETE/1000) | D73: =IF(ABS(B73-1000)<=1,"OK","VERIFICAR") | E73: =SUMIF($A$7:$A$67,A73,$L$7:$L$67)

Sheet 07_BOM_VERSION
A1: BOM VERSION
A2: Historico versionado de formulas. Nunca sobrescrever; criar nova versao com vigencia.
A4: Legenda: | B4: INPUT (editavel) | D4: FORMULA | F4: LINKED (de outra aba) | H4: CONTROL | J4: ALERT | L4: CHAVE/ID
A6: FORMULA_ID | B6: PRODUCT_ID | C6: Versao | D6: Motivo alteracao | E6: Vigencia ini | F6: Vigencia fim | G6: Aprovador | H6: Status
A7: F-P001 | B7: P001 | C7: v1 | D7: Versao base 2026 | E7: 2026-01-01 | G7: Eng. Tecnico | H7: Vigente
A8: F-P002 | B8: P002 | C8: v1 | D8: Versao base 2026 | E8: 2026-01-01 | G8: Eng. Tecnico | H8: Vigente
A9: F-P003 | B9: P003 | C9: v1 | D9: Versao base 2026 | E9: 2026-01-01 | G9: Eng. Tecnico | H9: Vigente
A11: ^ Linhas acima = dados DEMO (marcados). Abaixo: campos de entrada em branco para dados reais.

Sheet 09_LANDED_COST
A1: LANDED COST
A2: LANDED NET = bruto - desconto - rebate + frete + seguro + descarga + armazenagem + trib.nao-recup - creditos recuperaveis. Nunca usar preco de NF puro.
A4: Legenda: | B4: INPUT (editavel) | D4: FORMULA | F4: LINKED (de outra aba) | H4: CONTROL | J4: ALERT | L4: CHAVE/ID
A6: MATERIAL_ID | B6: SUPPLIER_ID | C6: PERIOD | D6: Unid | E6: Preco bruto (R$/un) | F6: (-) Desconto incond. | G6: (-) Rebate atribuivel | H6: (+) Frete inbound | I6: (+) Seguro | J6: (+) Descarga | K6: (+) Armazenag. | L6: (+) Trib. nao recuperavel | M6: (-) Creditos recuperaveis | N6: LANDED NET (R$/un) | O6: Fator un->t | P6: LANDED NET (R$/t) | Q6: Desembolso financeiro | R6: Credito fiscal | S6: Custo contabil
A7: M001 | B7: S001 | C7: 2026-03 | D7: t | E7: 700 | F7: 20 | G7: 10 | H7: 45 | I7: 3 | J7: 8 | K7: 6 | L7: 0 | M7: 92 | N7: =E7-F7-G7+H7+I7+J7+K7+L7-M7 | O7: =IF(D7="kg",1000,1) | P7: =N7*O7 | Q7: =E7-F7-G7+H7+I7+J7+K7+L7 | R7: =M7 | S7: =N7
A8: M002 | B8: S002 | C8: 2026-03 | D8: t | E8: 55 | F8: 0 | G8: 0 | H8: 22 | I8: 1 | J8: 5 | K8: 3 | L8: 0 | M8: 20 | N8: =E8-F8-G8+H8+I8+J8+K8+L8-M8 | O8: =IF(D8="kg",1000,1) | P8: =N8*O8 | Q8: =E8-F8-G8+H8+I8+J8+K8+L8 | R8: =M8 | S8: =N8
A9: M003 | B9: S001 | C9: 2026-03 | D9: t | E9: 520 | F9: 15 | G9: 0 | H9: 40 | I9: 2 | J9: 6 | K9: 4 | L9: 0 | M9: 72 | N9: =E9-F9-G9+H9+I9+J9+K9+L9-M9 | O9: =IF(D9="kg",1000,1) | P9: =N9*O9 | Q9: =E9-F9-G9+H9+I9+J9+K9+L9 | R9: =M9 | S9: =N9
A10: M004 | B10: S003 | C10: 2026-03 | D10: kg | E10: 19 | F10: 0.4 | G10: 0 | H10: 0.6 | I10: 0.05 | J10: 0.1 | K10: 0.05 | L10: 0 | M10: 2.4 | N10: =E10-F10-G10+H10+I10+J10+K10+L10-M10 | O10: =IF(D10="kg",1000,1) | P10: =N10*O10 | Q10: =E10-F10-G10+H10+I10+J10+K10+L10 | R10: =M10 | S10: =N10
A11: M005 | B11: S003 | C11: 2026-03 | D11: kg | E11: 9.5 | F11: 0.2 | G11: 0 | H11: 0.4 | I11: 0.03 | J11: 0.05 | K11: 0.03 | L11: 0 | M11: 1.2 | N11: =E11-F11-G11+H11+I11+J11+K11+L11-M11 | O11: =IF(D11="kg",1000,1) | P11: =N11*O11 | Q11: =E11-F11-G11+H11+I11+J11+K11+L11 | R11: =M11 | S11: =N11
N12: =E12-F12-G12+H12+I12+J12+K12+L12-M12 | O12: =IF(D12="kg",1000,1) | P12: =N12*O12 | Q12: =E12-F12-G12+H12+I12+J12+K12+L12 | R12: =M12 | S12: =N12
N13: =E13-F13-G13+H13+I13+J13+K13+L13-M13 | O13: =IF(D13="kg",1000,1) | P13: =N13*O13 | Q13: =E13-F13-G13+H13+I13+J13+K13+L13 | R13: =M13 | S13: =N13
N14: =E14-F14-G14+H14+I14+J14+K14+L14-M14 | O14: =IF(D14="kg",1000,1) | P14: =N14*O14 | Q14: =E14-F14-G14+H14+I14+J14+K14+L14 | R14: =M14 | S14: =N14
N15: =E15-F15-G15+H15+I15+J15+K15+L15-M15 | O15: =IF(D15="kg",1000,1) | P15: =N15*O15 | Q15: =E15-F15-G15+H15+I15+J15+K15+L15 | R15: =M15 | S15: =N15
N16: =E16-F16-G16+H16+I16+J16+K16+L16-M16 | O16: =IF(D16="kg",1000,1) | P16: =N16*O16 | Q16: =E16-F16-G16+H16+I16+J16+K16+L16 | R16: =M16 | S16: =N16
N17: =E17-F17-G17+H17+I17+J17+K17+L17-M17 | O17: =IF(D17="kg",1000,1) | P17: =N17*O17 | Q17: =E17-F17-G17+H17+I17+J17+K17+L17 | R17: =M17 | S17: =N17
N18: =E18-F18-G18+H18+I18+J18+K18+L18-M18 | O18: =IF(D18="kg",1000,1) | P18: =N18*O18 | Q18: =E18-F18-G18+H18+I18+J18+K18+L18 | R18: =M18 | S18: =N18
N19: =E19-F19-G19+H19+I19+J19+K19+L19-M19 | O19: =IF(D19="kg",1000,1) | P19: =N19*O19 | Q19: =E19-F19-G19+H19+I19+J19+K19+L19 | R19: =M19 | S19: =N19
N20: =E20-F20-G20+H20+I20+J20+K20+L20-M20 | O20: =IF(D20="kg",1000,1) | P20: =N20*O20 | Q20: =E20-F20-G20+H20+I20+J20+K20+L20 | R20: =M20 | S20: =N20
N21: =E21-F21-G21+H21+I21+J21+K21+L21-M21 | O21: =IF(D21="kg",1000,1) | P21: =N21*O21 | Q21: =E21-F21-G21+H21+I21+J21+K21+L21 | R21: =M21 | S21: =N21
N22: =E22-F22-G22+H22+I22+J22+K22+L22-M22 | O22: =IF(D22="kg",1000,1) | P22: =N22*O22 | Q22: =E22-F22-G22+H22+I22+J22+K22+L22 | R22: =M22 | S22: =N22
N23: =E23-F23-G23+H23+I23+J23+K23+L23-M23 | O23: =IF(D23="kg",1000,1) | P23: =N23*O23 | Q23: =E23-F23-G23+H23+I23+J23+K23+L23 | R23: =M23 | S23: =N23
... N46: =E46-F46-G46+H46+I46+J46+K46+L46-M46 | O46: =IF(D46="kg",1000,1) | P46: =N46*O46 | Q46: =E46-F46-G46+H46+I46+J46+K46+L46 | R46: =M46 | S46: =N46

Sheet 10_TAX_RULES
A1: TAX RULES
A2: Nenhuma aliquota digitada dentro de formula de custo. Cada regra tem vigencia; reforma tributaria (CBS/IBS 2026-2033) por DATA, nunca sobrescrevendo a antiga.
A4: Legenda: | B4: INPUT (editavel) | D4: FORMULA | F4: LINKED (de outra aba) | H4: CONTROL | J4: ALERT | L4: CHAVE/ID
A6: RULE_ID | B6: Tributo | C6: UF | D6: Operacao | E6: NCM | F6: CFOP | G6: CST | H6: Aliq. nominal | I6: Beneficio | J6: % reducao | K6: Aliq. efetiva | L6: Gera credito? | M6: Fundo adic. | N6: Fonte | O6: Responsavel | P6: Vigencia ini | Q6: Vigencia fim | R6: Atualizado em | S6: Comentario
A7: TR001 | B7: ICMS | C7: CE | D7: Saida interna | E7: 3824.50.00 | F7: 5101 | G7: 51 | H7: 0.225 | I7: Reducao 80% | J7: 0.8 | K7: =H7*(1-J7) | L7: Nao | M7: 0
A8: TR002 | B8: ICMS | C8: CE | D8: Entrada MP | E8: 2523.29.10 | F8: 1101 | G8: 00 | H8: 0.18 | I8: Credito integral | J8: 0 | K8: =H8*(1-J8) | L8: Sim | M8: 0
A9: TR003 | B9: PIS | C9: - | D9: Saida | E9: - | F9: - | G9: - | H9: 0.0165 | I9: Nao cumulativo | J9: 0 | K9: =H9*(1-J9) | L9: Sim | M9: 0
A10: TR004 | B10: COFINS | C10: - | D10: Saida | E10: - | F10: - | G10: - | H10: 0.076 | I10: Nao cumulativo | J10: 0 | K10: =H10*(1-J10) | L10: Sim | M10: 0
A11: TR005 | B11: CBS | C11: - | D11: Saida (2027+) | E11: - | F11: - | G11: - | H11: 0 | I11: Reforma - preencher | J11: 0 | K11: =H11*(1-J11) | L11: Sim | M11: 0
A12: TR006 | B12: IBS | C12: - | D12: Saida (2029+) | E12: - | F12: - | G12: - | H12: 0 | I12: Reforma - preencher | J12: 0 | K12: =H12*(1-J12) | L12: Sim | M12: 0
A14: ^ Linhas acima = dados DEMO (marcados). Abaixo: campos de entrada em branco para dados reais.

Sheet 11_TAX_CREDITS
A1: TAX CREDITS
A2: Separar credito potencial, escriturado, utilizado e monetizado. So o efetivamente recuperavel reduz o Landed Net Cost (aba 09).
A4: Legenda: | B4: INPUT (editavel) | D4: FORMULA | F4: LINKED (de outra aba) | H4: CONTROL | J4: ALERT | L4: CHAVE/ID
A6: MATERIAL_ID | B6: PERIOD | C6: Base (R$) | D6: Credito ICMS potencial | E6: Credito PIS/COFINS potencial | F6: Credito escriturado | G6: Credito utilizado | H6: Credito monetizado | I6: Gap (pot.-util.) | J6: Fonte | K6: Responsavel | L6: Vigencia ini | M6: Vigencia fim | N6: Atualizado em | O6: Comentario
A7: M001 | B7: 2026-03 | C7: 100000 | D7: =C7*ICMS_NOMINAL | E7: =C7*(PIS_DEBITO+COFINS_DEBITO) | F7: 0 | G7: 0 | H7: 0 | I7: =D7+E7-G7
A8: M002 | B8: 2026-03 | C8: 50000 | D8: =C8*ICMS_NOMINAL | E8: =C8*(PIS_DEBITO+COFINS_DEBITO) | F8: 0 | G8: 0 | H8: 0 | I8: =D8+E8-G8
A10: ^ Linhas acima = dados DEMO (marcados). Abaixo: campos de entrada em branco para dados reais.

Sheet 15_RESOURCE_RATES
A1: RESOURCE RATES
A2: R$/hora = custo fixo / horas de CAPACIDADE PRATICA (nao a producao real). Base do custo de conversao e do unused capacity cost.
A4: Legenda: | B4: INPUT (editavel) | D4: FORMULA | F4: LINKED (de outra aba) | H4: CONTROL | J4: ALERT | L4: CHAVE/ID
A6: RESOURCE_ID | B6: Custo fixo R$/mes (dep+manut+outros) | C6: Horas praticas/mes | D6: R$/hora pratica
A7: RES-MIST1 | B7: =SUMIF('12_RESOURCES'!$A$7:$A$67,A7,'12_RESOURCES'!$G$7:$G$67)+SUMIF('12_RESOURCES'!$A$7:$A$67,A7,'12_RESOURCES'!$H$7:$H$67)+SUMIF('12_RESOURCES'!$A$7:$A$67,A7,'12_RESOURCES'!$I$7:$I$67) | C7: =SUMIF('12_RESOURCES'!$A$7:$A$67,A7,'12_RESOURCES'!$F$7:$F$67) | D7: =IFERROR(B7/C7,0)
A8: RES-MIST2 | B8: =SUMIF('12_RESOURCES'!$A$7:$A$67,A8,'12_RESOURCES'!$G$7:$G$67)+SUMIF('12_RESOURCES'!$A$7:$A$67,A8,'12_RESOURCES'!$H$7:$H$67)+SUMIF('12_RESOURCES'!$A$7:$A$67,A8,'12_RESOURCES'!$I$7:$I$67) | C8: =SUMIF('12_RESOURCES'!$A$7:$A$67,A8,'12_RESOURCES'!$F$7:$F$67) | D8: =IFERROR(B8/C8,0)

Sheet 16_STANDARD_TIMES
A1: STANDARD TIMES
A2: Consolida o routing (14) em h/t por produto. Base do custo de conversao padrao e do speed loss.
A4: Legenda: | B4: INPUT (editavel) | D4: FORMULA | F4: LINKED (de outra aba) | H4: CONTROL | J4: ALERT | L4: CHAVE/ID
A6: PRODUCT_ID | B6: Tempo padrao total h/t (soma routing) | C6: Velocidade padrao t/h
A7: P001 | B7: =SUMIF('14_ROUTINGS'!$B$7:$B$67,A7,'14_ROUTINGS'!$F$7:$F$67) | C7: =IFERROR(1/B7,0)
A8: P002 | B8: =SUMIF('14_ROUTINGS'!$B$7:$B$67,A8,'14_ROUTINGS'!$F$7:$F$67) | C8: =IFERROR(1/B8,0)
A9: P003 | B9: =SUMIF('14_ROUTINGS'!$B$7:$B$67,A9,'14_ROUTINGS'!$F$7:$F$67) | C9: =IFERROR(1/B9,0)

Sheet 17_PRODUCTION_OF
A1: PRODUCTION OF
A2: Produtividade medida por hora inicio/fim da OF/lote (NAO por jornada contratual). Reproc. separado. t/h = qtd boa / tempo.
A4: Legenda: | B4: INPUT (editavel) | D4: FORMULA | F4: LINKED (de outra aba) | H4: CONTROL | J4: ALERT | L4: CHAVE/ID
A6: OF_ID | B6: PRODUCT_ID | C6: FORMULA_ID | D6: Versao | E6: RESOURCE_ID | F6: Equipe | G6: Data | H6: Hora ini | I6: Hora fim | J6: Qtd progr. (t) | K6: Qtd produz. (t) | L6: Qtd BOA (t) | M6: Sacos | N6: Paletes | O6: Perdas (t) | P6: Reproc. (t) | Q6: Tempo (h) | R6: t/h | S6: Obs
A7: OF-2603-01 | B7: P001 | C7: F-P001 | D7: v1 | E7: RES-MIST1 | F7: Turma A | G7: 2026-03-05 | H7: 06:00 | I7: 10:00 | J7: 400 | K7: 402 | L7: 400 | M7: =IFERROR(L7*1000/INDEX('03_PRODUCTS'!$G$7:$G$49,MATCH(B7,'03_PRODUCTS'!$A$7:$A$49,0)),"") | N7: =IFERROR(M7/INDEX('03_PRODUCTS'!$H$7:$H$49,MATCH(B7,'03_PRODUCTS'!$A$7:$A$49,0)),"") | O7: =K7-L7-P7 | P7: 0 | Q7: =IFERROR((TIMEVALUE(I7)-TIMEVALUE(H7))*24,"") | R7: =IFERROR(L7/Q7,"")
A8: OF-2603-02 | B8: P002 | C8: F-P002 | D8: v1 | E8: RES-MIST1 | F8: Turma A | G8: 2026-03-06 | H8: 06:00 | I8: 11:00 | J8: 250 | K8: 251 | L8: 250 | M8: =IFERROR(L8*1000/INDEX('03_PRODUCTS'!$G$7:$G$49,MATCH(B8,'03_PRODUCTS'!$A$7:$A$49,0)),"") | N8: =IFERROR(M8/INDEX('03_PRODUCTS'!$H$7:$H$49,MATCH(B8,'03_PRODUCTS'!$A$7:$A$49,0)),"") | O8: =K8-L8-P8 | P8: 0 | Q8: =IFERROR((TIMEVALUE(I8)-TIMEVALUE(H8))*24,"") | R8: =IFERROR(L8/Q8,"")
A9: OF-2603-03 | B9: P003 | C9: F-P003 | D9: v1 | E9: RES-MIST2 | F9: Turma B | G9: 2026-03-07 | H9: 07:00 | I9: 10:00 | J9: 120 | K9: 121 | L9: 120 | M9: =IFERROR(L9*1000/INDEX('03_PRODUCTS'!$G$7:$G$49,MATCH(B9,'03_PRODUCTS'!$A$7:$A$49,0)),"") | N9: =IFERROR(M9/INDEX('03_PRODUCTS'!$H$7:$H$49,MATCH(B9,'03_PRODUCTS'!$A$7:$A$49,0)),"") | O9: =K9-L9-P9 | P9: 0.5 | Q9: =IFERROR((TIMEVALUE(I9)-TIMEVALUE(H9))*24,"") | R9: =IFERROR(L9/Q9,"")

Sheet 18_ACTUAL_CONSUMPTION
A1: ACTUAL CONSUMPTION
A2: Base do Actual Cost. Act qtd = act kg/t /1000 x good tons. Act custo = act qtd x act preco.
A4: Legenda: | B4: INPUT (editavel) | D4: FORMULA | F4: LINKED (de outra aba) | H4: CONTROL | J4: ALERT | L4: CHAVE/ID
A6: OF_ID | B6: PRODUCT_ID | C6: MATERIAL_ID | D6: Good tons (link) | E6: Act kg/t (real) | F6: Act qtd (t) | G6: Act preco R$/t (real) | H6: Act custo (R$) | I6: KEY (prod|mat)
A7: OF-2603-01 | B7: P001 | C7: M001 | D7: =IFERROR(INDEX('17_PRODUCTION_OF'!$L$7:$L$47,MATCH(A7,'17_PRODUCTION_OF'!$A$7:$A$47,0)),0) | E7: 255 | F7: =E7/1000*D7 | G7: 660 | H7: =F7*G7 | I7: =B7&"|"&C7
A8: OF-2603-01 | B8: P001 | C8: M002 | D8: =IFERROR(INDEX('17_PRODUCTION_OF'!$L$7:$L$47,MATCH(A8,'17_PRODUCTION_OF'!$A$7:$A$47,0)),0) | E8: 700 | F8: =E8/1000*D8 | G8: 66 | H8: =F8*G8 | I8: =B8&"|"&C8
A9: OF-2603-01 | B9: P001 | C9: M003 | D9: =IFERROR(INDEX('17_PRODUCTION_OF'!$L$7:$L$47,MATCH(A9,'17_PRODUCTION_OF'!$A$7:$A$47,0)),0) | E9: 45 | F9: =E9/1000*D9 | G9: 485 | H9: =F9*G9 | I9: =B9&"|"&C9
A10: OF-2603-01 | B10: P001 | C10: M004 | D10: =IFERROR(INDEX('17_PRODUCTION_OF'!$L$7:$L$47,MATCH(A10,'17_PRODUCTION_OF'!$A$7:$A$47,0)),0) | E10: 5 | F10: =E10/1000*D10 | G10: 17000 | H10: =F10*G10 | I10: =B10&"|"&C10
A11: OF-2603-02 | B11: P002 | C11: M001 | D11: =IFERROR(INDEX('17_PRODUCTION_OF'!$L$7:$L$47,MATCH(A11,'17_PRODUCTION_OF'!$A$7:$A$47,0)),0) | E11: 300 | F11: =E11/1000*D11 | G11: 660 | H11: =F11*G11 | I11: =B11&"|"&C11
A12: OF-2603-02 | B12: P002 | C12: M002 | D12: =IFERROR(INDEX('17_PRODUCTION_OF'!$L$7:$L$47,MATCH(A12,'17_PRODUCTION_OF'!$A$7:$A$47,0)),0) | E12: 655 | F12: =E12/1000*D12 | G12: 66 | H12: =F12*G12 | I12: =B12&"|"&C12
A13: OF-2603-02 | B13: P002 | C13: M003 | D13: =IFERROR(INDEX('17_PRODUCTION_OF'!$L$7:$L$47,MATCH(A13,'17_PRODUCTION_OF'!$A$7:$A$47,0)),0) | E13: 45 | F13: =E13/1000*D13 | G13: 485 | H13: =F13*G13 | I13: =B13&"|"&C13
A14: OF-2603-02 | B14: P002 | C14: M004 | D14: =IFERROR(INDEX('17_PRODUCTION_OF'!$L$7:$L$47,MATCH(A14,'17_PRODUCTION_OF'!$A$7:$A$47,0)),0) | E14: 5 | F14: =E14/1000*D14 | G14: 17000 | H14: =F14*G14 | I14: =B14&"|"&C14
A15: OF-2603-03 | B15: P003 | C15: M001 | D15: =IFERROR(INDEX('17_PRODUCTION_OF'!$L$7:$L$47,MATCH(A15,'17_PRODUCTION_OF'!$A$7:$A$47,0)),0) | E15: 350 | F15: =E15/1000*D15 | G15: 660 | H15: =F15*G15 | I15: =B15&"|"&C15
A16: OF-2603-03 | B16: P003 | C16: M002 | D16: =IFERROR(INDEX('17_PRODUCTION_OF'!$L$7:$L$47,MATCH(A16,'17_PRODUCTION_OF'!$A$7:$A$47,0)),0) | E16: 600 | F16: =E16/1000*D16 | G16: 66 | H16: =F16*G16 | I16: =B16&"|"&C16
A17: OF-2603-03 | B17: P003 | C17: M004 | D17: =IFERROR(INDEX('17_PRODUCTION_OF'!$L$7:$L$47,MATCH(A17,'17_PRODUCTION_OF'!$A$7:$A$47,0)),0) | E17: 8 | F17: =E17/1000*D17 | G17: 17000 | H17: =F17*G17 | I17: =B17&"|"&C17
A18: OF-2603-03 | B18: P003 | C18: M005 | D18: =IFERROR(INDEX('17_PRODUCTION_OF'!$L$7:$L$47,MATCH(A18,'17_PRODUCTION_OF'!$A$7:$A$47,0)),0) | E18: 42 | F18: =E18/1000*D18 | G18: 8610 | H18: =F18*G18 | I18: =B18&"|"&C18
D19: =IF(A19="","",IFERROR(INDEX('17_PRODUCTION_OF'!$L$7:$L$47,MATCH(A19,'17_PRODUCTION_OF'!$A$7:$A$47,0)),0)) | F19: =IF(E19="","",E19/1000*D19) | H19: =IF(F19="","",F19*G19) | I19: =IF(B19="","",B19&"|"&C19)
D20: =IF(A20="","",IFERROR(INDEX('17_PRODUCTION_OF'!$L$7:$L$47,MATCH(A20,'17_PRODUCTION_OF'!$A$7:$A$47,0)),0)) | F20: =IF(E20="","",E20/1000*D20) | H20: =IF(F20="","",F20*G20) | I20: =IF(B20="","",B20&"|"&C20)
D21: =IF(A21="","",IFERROR(INDEX('17_PRODUCTION_OF'!$L$7:$L$47,MATCH(A21,'17_PRODUCTION_OF'!$A$7:$A$47,0)),0)) | F21: =IF(E21="","",E21/1000*D21) | H21: =IF(F21="","",F21*G21) | I21: =IF(B21="","",B21&"|"&C21)
D22: =IF(A22="","",IFERROR(INDEX('17_PRODUCTION_OF'!$L$7:$L$47,MATCH(A22,'17_PRODUCTION_OF'!$A$7:$A$47,0)),0)) | F22: =IF(E22="","",E22/1000*D22) | H22: =IF(F22="","",F22*G22) | I22: =IF(B22="","",B22&"|"&C22)
D23: =IF(A23="","",IFERROR(INDEX('17_PRODUCTION_OF'!$L$7:$L$47,MATCH(A23,'17_PRODUCTION_OF'!$A$7:$A$47,0)),0)) | F23: =IF(E23="","",E23/1000*D23) | H23: =IF(F23="","",F23*G23) | I23: =IF(B23="","",B23&"|"&C23)
D24: =IF(A24="","",IFERROR(INDEX('17_PRODUCTION_OF'!$L$7:$L$47,MATCH(A24,'17_PRODUCTION_OF'!$A$7:$A$47,0)),0)) | F24: =IF(E24="","",E24/1000*D24) | H24: =IF(F24="","",F24*G24) | I24: =IF(B24="","",B24&"|"&C24)
D25: =IF(A25="","",IFERROR(INDEX('17_PRODUCTION_OF'!$L$7:$L$47,MATCH(A25,'17_PRODUCTION_OF'!$A$7:$A$47,0)),0)) | F25: =IF(E25="","",E25/1000*D25) | H25: =IF(F25="","",F25*G25) | I25: =IF(B25="","",B25&"|"&C25)
D26: =IF(A26="","",IFERROR(INDEX('17_PRODUCTION_OF'!$L$7:$L$47,MATCH(A26,'17_PRODUCTION_OF'!$A$7:$A$47,0)),0)) | F26: =IF(E26="","",E26/1000*D26) | H26: =IF(F26="","",F26*G26) | I26: =IF(B26="","",B26&"|"&C26)
D27: =IF(A27="","",IFERROR(INDEX('17_PRODUCTION_OF'!$L$7:$L$47,MATCH(A27,'17_PRODUCTION_OF'!$A$7:$A$47,0)),0)) | F27: =IF(E27="","",E27/1000*D27) | H27: =IF(F27="","",F27*G27) | I27: =IF(B27="","",B27&"|"&C27)
D28: =IF(A28="","",IFERROR(INDEX('17_PRODUCTION_OF'!$L$7:$L$47,MATCH(A28,'17_PRODUCTION_OF'!$A$7:$A$47,0)),0)) | F28: =IF(E28="","",E28/1000*D28) | H28: =IF(F28="","",F28*G28) | I28: =IF(B28="","",B28&"|"&C28)
D29: =IF(A29="","",IFERROR(INDEX('17_PRODUCTION_OF'!$L$7:$L$47,MATCH(A29,'17_PRODUCTION_OF'!$A$7:$A$47,0)),0)) | F29: =IF(E29="","",E29/1000*D29) | H29: =IF(F29="","",F29*G29) | I29: =IF(B29="","",B29&"|"&C29)
D30: =IF(A30="","",IFERROR(INDEX('17_PRODUCTION_OF'!$L$7:$L$47,MATCH(A30,'17_PRODUCTION_OF'!$A$7:$A$47,0)),0)) | F30: =IF(E30="","",E30/1000*D30) | H30: =IF(F30="","",F30*G30) | I30: =IF(B30="","",B30&"|"&C30)
... D66: =IF(A66="","",IFERROR(INDEX('17_PRODUCTION_OF'!$L$7:$L$47,MATCH(A66,'17_PRODUCTION_OF'!$A$7:$A$47,0)),0)) | F66: =IF(E66="","",E66/1000*D66) | H66: =IF(F66="","",F66*G66) | I66: =IF(B66="","",B66&"|"&C66)

Sheet 26_STANDARD_COST
A1: STANDARD COST
A2: Material std = SUMIF do BOM (kg/t x landed R$/t). Conversao std vem do routing (input aqui). Unidade base: R$/tonelada boa produzida.
A4: Legenda: | B4: INPUT (editavel) | D4: FORMULA | F4: LINKED (de outra aba) | H4: CONTROL | J4: ALERT | L4: CHAVE/ID
A6: PRODUCT_ID | B6: Descricao | C6: Good tons (link OF) | D6: Material std R$/t | E6: Conversao std R$/t | F6: TOTAL STD R$/t | G6: TOTAL STD R$
A7: P001 | B7: Multiuso | C7: =SUMIF('17_PRODUCTION_OF'!$B$7:$B$47,A7,'17_PRODUCTION_OF'!$L$7:$L$47) | D7: =SUMIF('06_BOM'!$A$7:$A$67,A7,'06_BOM'!$L$7:$L$67) | E7: 38 | F7: =D7+E7 | G7: =F7*C7
A8: P002 | B8: Argamassa AC-III | C8: =SUMIF('17_PRODUCTION_OF'!$B$7:$B$47,A8,'17_PRODUCTION_OF'!$L$7:$L$47) | D8: =SUMIF('06_BOM'!$A$7:$A$67,A8,'06_BOM'!$L$7:$L$67) | E8: 42 | F8: =D8+E8 | G8: =F8*C8
A9: P003 | B9: Rejunte | C9: =SUMIF('17_PRODUCTION_OF'!$B$7:$B$47,A9,'17_PRODUCTION_OF'!$L$7:$L$47) | D9: =SUMIF('06_BOM'!$A$7:$A$67,A9,'06_BOM'!$L$7:$L$67) | E9: 55 | F9: =D9+E9 | G9: =F9*C9

Sheet 27_ACTUAL_COST
A1: ACTUAL COST
A2: Material real = SUMIFS de 18_ACTUAL_CONSUMPTION. Conversao real (input; origem apontamento). TOTAL ACT R$/t e o KPI Material+Conversao por tonelada boa.
A4: Legenda: | B4: INPUT (editavel) | D4: FORMULA | F4: LINKED (de outra aba) | H4: CONTROL | J4: ALERT | L4: CHAVE/ID
A6: PRODUCT_ID | B6: Good tons (link) | C6: Material act R$ | D6: Material act R$/t | E6: Conversao act R$/t | F6: Conversao act R$ | G6: TOTAL ACT R$ | H6: TOTAL ACT R$/t
A7: P001 | B7: =SUMIF('17_PRODUCTION_OF'!$B$7:$B$47,A7,'17_PRODUCTION_OF'!$L$7:$L$47) | C7: =SUMIF('18_ACTUAL_CONSUMPTION'!$B$7:$B$67,A7,'18_ACTUAL_CONSUMPTION'!$H$7:$H$67) | D7: =IFERROR(C7/B7,0) | E7: 41 | F7: =E7*B7 | G7: =C7+F7 | H7: =IFERROR(G7/B7,0)
A8: P002 | B8: =SUMIF('17_PRODUCTION_OF'!$B$7:$B$47,A8,'17_PRODUCTION_OF'!$L$7:$L$47) | C8: =SUMIF('18_ACTUAL_CONSUMPTION'!$B$7:$B$67,A8,'18_ACTUAL_CONSUMPTION'!$H$7:$H$67) | D8: =IFERROR(C8/B8,0) | E8: 42 | F8: =E8*B8 | G8: =C8+F8 | H8: =IFERROR(G8/B8,0)
A9: P003 | B9: =SUMIF('17_PRODUCTION_OF'!$B$7:$B$47,A9,'17_PRODUCTION_OF'!$L$7:$L$47) | C9: =SUMIF('18_ACTUAL_CONSUMPTION'!$B$7:$B$67,A9,'18_ACTUAL_CONSUMPTION'!$H$7:$H$67) | D9: =IFERROR(C9/B9,0) | E9: 58 | F9: =E9*B9 | G9: =C9+F9 | H9: =IFERROR(G9/B9,0)

Sheet 28_VARIANCES
A1: VARIANCES
A2: PPV=(Act-Std preco)xAct qtd ; Usage=(Act-Std qtd)xStd preco. Std cost + PPV + Usage = Act cost (Residual->0). Mix/Yield e conversao no bloco resumo.
A4: Legenda: | B4: INPUT (editavel) | D4: FORMULA | F4: LINKED (de outra aba) | H4: CONTROL | J4: ALERT | L4: CHAVE/ID
A6: PRODUCT_ID | B6: MATERIAL_ID | C6: Good tons | D6: Std kg/t | E6: Act kg/t | F6: Std R$/t | G6: Act R$/t | H6: Std qtd (t) | I6: Act qtd (t) | J6: Std cost R$ | K6: Act cost R$ | L6: PPV R$ | M6: Usage R$ | N6: Residual
A7: P001 | B7: M001 | C7: =SUMIF('17_PRODUCTION_OF'!$B$7:$B$47,A7,'17_PRODUCTION_OF'!$L$7:$L$47) | D7: =IFERROR(INDEX('06_BOM'!$E$7:$E$67,MATCH(A7&"|"&B7,'06_BOM'!$M$7:$M$67,0)),0) | E7: =IFERROR(INDEX('18_ACTUAL_CONSUMPTION'!$E$7:$E$67,MATCH(A7&"|"&B7,'18_ACTUAL_CONSUMPTION'!$I$7:$I$67,0)),0) | F7: =IFERROR(INDEX('09_LANDED_COST'!$P$7:$P$47,MATCH(B7,'09_LANDED_COST'!$A$7:$A$47,0)),0) | G7: =IFERROR(INDEX('18_ACTUAL_CONSUMPTION'!$G$7:$G$67,MATCH(A7&"|"&B7,'18_ACTUAL_CONSUMPTION'!$I$7:$I$67,0)),0) | H7: =D7/1000*C7 | I7: =E7/1000*C7 | J7: =H7*F7 | K7: =I7*G7 | L7: =(G7-F7)*I7 | M7: =(I7-H7)*F7 | N7: =K7-J7-L7-M7
A8: P001 | B8: M002 | C8: =SUMIF('17_PRODUCTION_OF'!$B$7:$B$47,A8,'17_PRODUCTION_OF'!$L$7:$L$47) | D8: =IFERROR(INDEX('06_BOM'!$E$7:$E$67,MATCH(A8&"|"&B8,'06_BOM'!$M$7:$M$67,0)),0) | E8: =IFERROR(INDEX('18_ACTUAL_CONSUMPTION'!$E$7:$E$67,MATCH(A8&"|"&B8,'18_ACTUAL_CONSUMPTION'!$I$7:$I$67,0)),0) | F8: =IFERROR(INDEX('09_LANDED_COST'!$P$7:$P$47,MATCH(B8,'09_LANDED_COST'!$A$7:$A$47,0)),0) | G8: =IFERROR(INDEX('18_ACTUAL_CONSUMPTION'!$G$7:$G$67,MATCH(A8&"|"&B8,'18_ACTUAL_CONSUMPTION'!$I$7:$I$67,0)),0) | H8: =D8/1000*C8 | I8: =E8/1000*C8 | J8: =H8*F8 | K8: =I8*G8 | L8: =(G8-F8)*I8 | M8: =(I8-H8)*F8 | N8: =K8-J8-L8-M8
A9: P001 | B9: M003 | C9: =SUMIF('17_PRODUCTION_OF'!$B$7:$B$47,A9,'17_PRODUCTION_OF'!$L$7:$L$47) | D9: =IFERROR(INDEX('06_BOM'!$E$7:$E$67,MATCH(A9&"|"&B9,'06_BOM'!$M$7:$M$67,0)),0) | E9: =IFERROR(INDEX('18_ACTUAL_CONSUMPTION'!$E$7:$E$67,MATCH(A9&"|"&B9,'18_ACTUAL_CONSUMPTION'!$I$7:$I$67,0)),0) | F9: =IFERROR(INDEX('09_LANDED_COST'!$P$7:$P$47,MATCH(B9,'09_LANDED_COST'!$A$7:$A$47,0)),0) | G9: =IFERROR(INDEX('18_ACTUAL_CONSUMPTION'!$G$7:$G$67,MATCH(A9&"|"&B9,'18_ACTUAL_CONSUMPTION'!$I$7:$I$67,0)),0) | H9: =D9/1000*C9 | I9: =E9/1000*C9 | J9: =H9*F9 | K9: =I9*G9 | L9: =(G9-F9)*I9 | M9: =(I9-H9)*F9 | N9: =K9-J9-L9-M9
A10: P001 | B10: M004 | C10: =SUMIF('17_PRODUCTION_OF'!$B$7:$B$47,A10,'17_PRODUCTION_OF'!$L$7:$L$47) | D10: =IFERROR(INDEX('06_BOM'!$E$7:$E$67,MATCH(A10&"|"&B10,'06_BOM'!$M$7:$M$67,0)),0) | E10: =IFERROR(INDEX('18_ACTUAL_CONSUMPTION'!$E$7:$E$67,MATCH(A10&"|"&B10,'18_ACTUAL_CONSUMPTION'!$I$7:$I$67,0)),0) | F10: =IFERROR(INDEX('09_LANDED_COST'!$P$7:$P$47,MATCH(B10,'09_LANDED_COST'!$A$7:$A$47,0)),0) | G10: =IFERROR(INDEX('18_ACTUAL_CONSUMPTION'!$G$7:$G$67,MATCH(A10&"|"&B10,'18_ACTUAL_CONSUMPTION'!$I$7:$I$67,0)),0) | H10: =D10/1000*C10 | I10: =E10/1000*C10 | J10: =H10*F10 | K10: =I10*G10 | L10: =(G10-F10)*I10 | M10: =(I10-H10)*F10 | N10: =K10-J10-L10-M10
A11: P002 | B11: M001 | C11: =SUMIF('17_PRODUCTION_OF'!$B$7:$B$47,A11,'17_PRODUCTION_OF'!$L$7:$L$47) | D11: =IFERROR(INDEX('06_BOM'!$E$7:$E$67,MATCH(A11&"|"&B11,'06_BOM'!$M$7:$M$67,0)),0) | E11: =IFERROR(INDEX('18_ACTUAL_CONSUMPTION'!$E$7:$E$67,MATCH(A11&"|"&B11,'18_ACTUAL_CONSUMPTION'!$I$7:$I$67,0)),0) | F11: =IFERROR(INDEX('09_LANDED_COST'!$P$7:$P$47,MATCH(B11,'09_LANDED_COST'!$A$7:$A$47,0)),0) | G11: =IFERROR(INDEX('18_ACTUAL_CONSUMPTION'!$G$7:$G$67,MATCH(A11&"|"&B11,'18_ACTUAL_CONSUMPTION'!$I$7:$I$67,0)),0) | H11: =D11/1000*C11 | I11: =E11/1000*C11 | J11: =H11*F11 | K11: =I11*G11 | L11: =(G11-F11)*I11 | M11: =(I11-H11)*F11 | N11: =K11-J11-L11-M11
A12: P002 | B12: M002 | C12: =SUMIF('17_PRODUCTION_OF'!$B$7:$B$47,A12,'17_PRODUCTION_OF'!$L$7:$L$47) | D12: =IFERROR(INDEX('06_BOM'!$E$7:$E$67,MATCH(A12&"|"&B12,'06_BOM'!$M$7:$M$67,0)),0) | E12: =IFERROR(INDEX('18_ACTUAL_CONSUMPTION'!$E$7:$E$67,MATCH(A12&"|"&B12,'18_ACTUAL_CONSUMPTION'!$I$7:$I$67,0)),0) | F12: =IFERROR(INDEX('09_LANDED_COST'!$P$7:$P$47,MATCH(B12,'09_LANDED_COST'!$A$7:$A$47,0)),0) | G12: =IFERROR(INDEX('18_ACTUAL_CONSUMPTION'!$G$7:$G$67,MATCH(A12&"|"&B12,'18_ACTUAL_CONSUMPTION'!$I$7:$I$67,0)),0) | H12: =D12/1000*C12 | I12: =E12/1000*C12 | J12: =H12*F12 | K12: =I12*G12 | L12: =(G12-F12)*I12 | M12: =(I12-H12)*F12 | N12: =K12-J12-L12-M12
A13: P002 | B13: M003 | C13: =SUMIF('17_PRODUCTION_OF'!$B$7:$B$47,A13,'17_PRODUCTION_OF'!$L$7:$L$47) | D13: =IFERROR(INDEX('06_BOM'!$E$7:$E$67,MATCH(A13&"|"&B13,'06_BOM'!$M$7:$M$67,0)),0) | E13: =IFERROR(INDEX('18_ACTUAL_CONSUMPTION'!$E$7:$E$67,MATCH(A13&"|"&B13,'18_ACTUAL_CONSUMPTION'!$I$7:$I$67,0)),0) | F13: =IFERROR(INDEX('09_LANDED_COST'!$P$7:$P$47,MATCH(B13,'09_LANDED_COST'!$A$7:$A$47,0)),0) | G13: =IFERROR(INDEX('18_ACTUAL_CONSUMPTION'!$G$7:$G$67,MATCH(A13&"|"&B13,'18_ACTUAL_CONSUMPTION'!$I$7:$I$67,0)),0) | H13: =D13/1000*C13 | I13: =E13/1000*C13 | J13: =H13*F13 | K13: =I13*G13 | L13: =(G13-F13)*I13 | M13: =(I13-H13)*F13 | N13: =K13-J13-L13-M13
A14: P002 | B14: M004 | C14: =SUMIF('17_PRODUCTION_OF'!$B$7:$B$47,A14,'17_PRODUCTION_OF'!$L$7:$L$47) | D14: =IFERROR(INDEX('06_BOM'!$E$7:$E$67,MATCH(A14&"|"&B14,'06_BOM'!$M$7:$M$67,0)),0) | E14: =IFERROR(INDEX('18_ACTUAL_CONSUMPTION'!$E$7:$E$67,MATCH(A14&"|"&B14,'18_ACTUAL_CONSUMPTION'!$I$7:$I$67,0)),0) | F14: =IFERROR(INDEX('09_LANDED_COST'!$P$7:$P$47,MATCH(B14,'09_LANDED_COST'!$A$7:$A$47,0)),0) | G14: =IFERROR(INDEX('18_ACTUAL_CONSUMPTION'!$G$7:$G$67,MATCH(A14&"|"&B14,'18_ACTUAL_CONSUMPTION'!$I$7:$I$67,0)),0) | H14: =D14/1000*C14 | I14: =E14/1000*C14 | J14: =H14*F14 | K14: =I14*G14 | L14: =(G14-F14)*I14 | M14: =(I14-H14)*F14 | N14: =K14-J14-L14-M14
A15: P003 | B15: M001 | C15: =SUMIF('17_PRODUCTION_OF'!$B$7:$B$47,A15,'17_PRODUCTION_OF'!$L$7:$L$47) | D15: =IFERROR(INDEX('06_BOM'!$E$7:$E$67,MATCH(A15&"|"&B15,'06_BOM'!$M$7:$M$67,0)),0) | E15: =IFERROR(INDEX('18_ACTUAL_CONSUMPTION'!$E$7:$E$67,MATCH(A15&"|"&B15,'18_ACTUAL_CONSUMPTION'!$I$7:$I$67,0)),0) | F15: =IFERROR(INDEX('09_LANDED_COST'!$P$7:$P$47,MATCH(B15,'09_LANDED_COST'!$A$7:$A$47,0)),0) | G15: =IFERROR(INDEX('18_ACTUAL_CONSUMPTION'!$G$7:$G$67,MATCH(A15&"|"&B15,'18_ACTUAL_CONSUMPTION'!$I$7:$I$67,0)),0) | H15: =D15/1000*C15 | I15: =E15/1000*C15 | J15: =H15*F15 | K15: =I15*G15 | L15: =(G15-F15)*I15 | M15: =(I15-H15)*F15 | N15: =K15-J15-L15-M15
A16: P003 | B16: M002 | C16: =SUMIF('17_PRODUCTION_OF'!$B$7:$B$47,A16,'17_PRODUCTION_OF'!$L$7:$L$47) | D16: =IFERROR(INDEX('06_BOM'!$E$7:$E$67,MATCH(A16&"|"&B16,'06_BOM'!$M$7:$M$67,0)),0) | E16: =IFERROR(INDEX('18_ACTUAL_CONSUMPTION'!$E$7:$E$67,MATCH(A16&"|"&B16,'18_ACTUAL_CONSUMPTION'!$I$7:$I$67,0)),0) | F16: =IFERROR(INDEX('09_LANDED_COST'!$P$7:$P$47,MATCH(B16,'09_LANDED_COST'!$A$7:$A$47,0)),0) | G16: =IFERROR(INDEX('18_ACTUAL_CONSUMPTION'!$G$7:$G$67,MATCH(A16&"|"&B16,'18_ACTUAL_CONSUMPTION'!$I$7:$I$67,0)),0) | H16: =D16/1000*C16 | I16: =E16/1000*C16 | J16: =H16*F16 | K16: =I16*G16 | L16: =(G16-F16)*I16 | M16: =(I16-H16)*F16 | N16: =K16-J16-L16-M16
A17: P003 | B17: M004 | C17: =SUMIF('17_PRODUCTION_OF'!$B$7:$B$47,A17,'17_PRODUCTION_OF'!$L$7:$L$47) | D17: =IFERROR(INDEX('06_BOM'!$E$7:$E$67,MATCH(A17&"|"&B17,'06_BOM'!$M$7:$M$67,0)),0) | E17: =IFERROR(INDEX('18_ACTUAL_CONSUMPTION'!$E$7:$E$67,MATCH(A17&"|"&B17,'18_ACTUAL_CONSUMPTION'!$I$7:$I$67,0)),0) | F17: =IFERROR(INDEX('09_LANDED_COST'!$P$7:$P$47,MATCH(B17,'09_LANDED_COST'!$A$7:$A$47,0)),0) | G17: =IFERROR(INDEX('18_ACTUAL_CONSUMPTION'!$G$7:$G$67,MATCH(A17&"|"&B17,'18_ACTUAL_CONSUMPTION'!$I$7:$I$67,0)),0) | H17: =D17/1000*C17 | I17: =E17/1000*C17 | J17: =H17*F17 | K17: =I17*G17 | L17: =(G17-F17)*I17 | M17: =(I17-H17)*F17 | N17: =K17-J17-L17-M17
A18: P003 | B18: M005 | C18: =SUMIF('17_PRODUCTION_OF'!$B$7:$B$47,A18,'17_PRODUCTION_OF'!$L$7:$L$47) | D18: =IFERROR(INDEX('06_BOM'!$E$7:$E$67,MATCH(A18&"|"&B18,'06_BOM'!$M$7:$M$67,0)),0) | E18: =IFERROR(INDEX('18_ACTUAL_CONSUMPTION'!$E$7:$E$67,MATCH(A18&"|"&B18,'18_ACTUAL_CONSUMPTION'!$I$7:$I$67,0)),0) | F18: =IFERROR(INDEX('09_LANDED_COST'!$P$7:$P$47,MATCH(B18,'09_LANDED_COST'!$A$7:$A$47,0)),0) | G18: =IFERROR(INDEX('18_ACTUAL_CONSUMPTION'!$G$7:$G$67,MATCH(A18&"|"&B18,'18_ACTUAL_CONSUMPTION'!$I$7:$I$67,0)),0) | H18: =D18/1000*C18 | I18: =E18/1000*C18 | J18: =H18*F18 | K18: =I18*G18 | L18: =(G18-F18)*I18 | M18: =(I18-H18)*F18 | N18: =K18-J18-L18-M18
A21: RESUMO POR PRODUTO — MIX/YIELD, CONVERSAO E RECONCILIACAO
A22: PRODUCT_ID | B22: Std mat R$ | C22: Act mat R$ | D22: PPV R$ | E22: Usage R$ | F22: Std qtd T | G22: Act qtd T | H22: wsp R$/t | I22: Yield R$ | J22: Mix R$ | K22: Conv var R$ | L22: Total var R$ | M22: Recon check
A23: P001 | B23: =SUMIF($A$7:$A$18,A23,$J$7:$J$18) | C23: =SUMIF($A$7:$A$18,A23,$K$7:$K$18) | D23: =SUMIF($A$7:$A$18,A23,$L$7:$L$18) | E23: =SUMIF($A$7:$A$18,A23,$M$7:$M$18) | F23: =SUMIF($A$7:$A$18,A23,$H$7:$H$18) | G23: =SUMIF($A$7:$A$18,A23,$I$7:$I$18) | H23: =IFERROR(B23/F23,0) | I23: =(G23-F23)*H23 | J23: =E23-I23 | K23: =(INDEX('27_ACTUAL_COST'!$E$7:$E$9,MATCH(A23,'27_ACTUAL_COST'!$A$7:$A$9,0))-INDEX('26_STANDARD_COST'!$E$7:$E$9,MATCH(A23,'26_STANDARD_COST'!$A$7:$A$9,0)))*INDEX('26_STANDARD_COST'!$C$7:$C$9,MATCH(A23,'26_STANDARD_COST'!$A$7:$A$9,0)) | L23: =D23+E23+K23 | M23: =ROUND(INDEX('26_STANDARD_COST'!$G$7:$G$9,MATCH(A23,'26_STANDARD_COST'!$A$7:$A$9,0))+L23-INDEX('27_ACTUAL_COST'!$G$7:$G$9,MATCH(A23,'27_ACTUAL_COST'!$A$7:$A$9,0)),2)
A24: P002 | B24: =SUMIF($A$7:$A$18,A24,$J$7:$J$18) | C24: =SUMIF($A$7:$A$18,A24,$K$7:$K$18) | D24: =SUMIF($A$7:$A$18,A24,$L$7:$L$18) | E24: =SUMIF($A$7:$A$18,A24,$M$7:$M$18) | F24: =SUMIF($A$7:$A$18,A24,$H$7:$H$18) | G24: =SUMIF($A$7:$A$18,A24,$I$7:$I$18) | H24: =IFERROR(B24/F24,0) | I24: =(G24-F24)*H24 | J24: =E24-I24 | K24: =(INDEX('27_ACTUAL_COST'!$E$7:$E$9,MATCH(A24,'27_ACTUAL_COST'!$A$7:$A$9,0))-INDEX('26_STANDARD_COST'!$E$7:$E$9,MATCH(A24,'26_STANDARD_COST'!$A$7:$A$9,0)))*INDEX('26_STANDARD_COST'!$C$7:$C$9,MATCH(A24,'26_STANDARD_COST'!$A$7:$A$9,0)) | L24: =D24+E24+K24 | M24: =ROUND(INDEX('26_STANDARD_COST'!$G$7:$G$9,MATCH(A24,'26_STANDARD_COST'!$A$7:$A$9,0))+L24-INDEX('27_ACTUAL_COST'!$G$7:$G$9,MATCH(A24,'27_ACTUAL_COST'!$A$7:$A$9,0)),2)
A25: P003 | B25: =SUMIF($A$7:$A$18,A25,$J$7:$J$18) | C25: =SUMIF($A$7:$A$18,A25,$K$7:$K$18) | D25: =SUMIF($A$7:$A$18,A25,$L$7:$L$18) | E25: =SUMIF($A$7:$A$18,A25,$M$7:$M$18) | F25: =SUMIF($A$7:$A$18,A25,$H$7:$H$18) | G25: =SUMIF($A$7:$A$18,A25,$I$7:$I$18) | H25: =IFERROR(B25/F25,0) | I25: =(G25-F25)*H25 | J25: =E25-I25 | K25: =(INDEX('27_ACTUAL_COST'!$E$7:$E$9,MATCH(A25,'27_ACTUAL_COST'!$A$7:$A$9,0))-INDEX('26_STANDARD_COST'!$E$7:$E$9,MATCH(A25,'26_STANDARD_COST'!$A$7:$A$9,0)))*INDEX('26_STANDARD_COST'!$C$7:$C$9,MATCH(A25,'26_STANDARD_COST'!$A$7:$A$9,0)) | L25: =D25+E25+K25 | M25: =ROUND(INDEX('26_STANDARD_COST'!$G$7:$G$9,MATCH(A25,'26_STANDARD_COST'!$A$7:$A$9,0))+L25-INDEX('27_ACTUAL_COST'!$G$7:$G$9,MATCH(A25,'27_ACTUAL_COST'!$A$7:$A$9,0)),2)
A27: Recon check = (Std total + Total var) - Act total -> deve ser 0,00 por construcao.

Sheet 29_CAPACITY
A1: CAPACITY
A2: Horas ociosas = praticas - usadas. Unused Capacity Cost = ociosas x R$/hora. Este custo fica VISIVEL, nao e rateado ao produto.
A4: Legenda: | B4: INPUT (editavel) | D4: FORMULA | F4: LINKED (de outra aba) | H4: CONTROL | J4: ALERT | L4: CHAVE/ID
A6: RESOURCE_ID | B6: Horas praticas (link) | C6: Horas usadas (link OF) | D6: Horas ociosas | E6: R$/hora (link) | F6: UNUSED CAPACITY COST R$
A7: RES-MIST1 | B7: =SUMIF('12_RESOURCES'!$A$7:$A$67,A7,'12_RESOURCES'!$F$7:$F$67) | C7: =SUMIF('17_PRODUCTION_OF'!$E$7:$E$47,A7,'17_PRODUCTION_OF'!$Q$7:$Q$47) | D7: =B7-C7 | E7: =IFERROR(INDEX('15_RESOURCE_RATES'!$D$7:$D$9,MATCH(A7,'15_RESOURCE_RATES'!$A$7:$A$9,0)),0) | F7: =D7*E7
A8: RES-MIST2 | B8: =SUMIF('12_RESOURCES'!$A$7:$A$67,A8,'12_RESOURCES'!$F$7:$F$67) | C8: =SUMIF('17_PRODUCTION_OF'!$E$7:$E$47,A8,'17_PRODUCTION_OF'!$Q$7:$Q$47) | D8: =B8-C8 | E8: =IFERROR(INDEX('15_RESOURCE_RATES'!$D$7:$D$9,MATCH(A8,'15_RESOURCE_RATES'!$A$7:$A$9,0)),0) | F8: =D8*E8
A10: Total unused capacity cost: | F10: =SUM(F7:F8)

Sheet 08_PURCHASES
A1: PURCHASES
A2: Base bruta de compras. Alimenta 09_LANDED_COST e PPV (preco real vs padrao).
A4: Legenda: | B4: INPUT (editavel) | D4: FORMULA | F4: LINKED (de outra aba) | H4: CONTROL | J4: ALERT | L4: CHAVE/ID
A6: PURCHASE_ID | B6: MATERIAL_ID | C6: SUPPLIER_ID | D6: Data | E6: NF | F6: Qtd | G6: Unid | H6: Preco bruto R$/un | I6: Desconto R$ | J6: Frete R$ | K6: ICMS destac. R$ | L6: PIS/COFINS R$ | M6: Fonte | N6: Responsavel | O6: Vigencia ini | P6: Vigencia fim | Q6: Atualizado em | R6: Comentario
A7: PC-001 | B7: M001 | C7: S001 | D7: 2026-03-02 | E7: 12345 | F7: 30 | G7: t | H7: 700 | I7: 600 | J7: 1350 | K7: 3780 | L7: 0
A8: PC-002 | B8: M002 | C8: S002 | D8: 2026-03-03 | E8: 12346 | F8: 60 | G8: t | H8: 55 | I8: 0 | J8: 1320 | K8: 594 | L8: 0
A10: ^ Linhas acima = dados DEMO (marcados). Abaixo: campos de entrada em branco para dados reais.

Sheet 12_RESOURCES
A1: RESOURCES
A2: Base do Resource Cost Model e da capacidade pratica.
A4: Legenda: | B4: INPUT (editavel) | D4: FORMULA | F4: LINKED (de outra aba) | H4: CONTROL | J4: ALERT | L4: CHAVE/ID
A6: RESOURCE_ID | B6: Descricao | C6: COST_CENTER_ID | D6: Cap. nominal (t/h) | E6: Cap. pratica (t/h) | F6: Horas disp./mes | G6: Depreciacao R$/mes | H6: Manut. fixa R$/mes | I6: Outros fixos R$/mes | J6: Fonte | K6: Responsavel | L6: Vigencia ini | M6: Vigencia fim | N6: Atualizado em | O6: Comentario
A7: RES-MIST1 | B7: Misturador industrial 1 | C7: CC-PROD | D7: 8 | E7: 6.5 | F7: 360 | G7: 8000 | H7: 3000 | I7: 2000
A8: RES-MIST2 | B8: Misturador industrial 2 | C8: CC-PROD | D8: 6 | E8: 5 | F8: 360 | G8: 6000 | H8: 2500 | I8: 1500
A10: ^ Linhas acima = dados DEMO (marcados). Abaixo: campos de entrada em branco para dados reais.

Sheet 13_COST_CENTERS
A1: COST CENTERS
A2: Estrutura de acumulacao. Reprocesso tem centro proprio (nao contamina equipe principal).
A4: Legenda: | B4: INPUT (editavel) | D4: FORMULA | F4: LINKED (de outra aba) | H4: CONTROL | J4: ALERT | L4: CHAVE/ID
A6: COST_CENTER_ID | B6: Descricao | C6: Tipo | D6: Responsavel | E6: Custo fixo mes R$ | F6: Fonte | G6: Responsavel | H6: Vigencia ini | I6: Vigencia fim | J6: Atualizado em | K6: Comentario
A7: CC-PROD | B7: Producao principal | C7: Produtivo | D7: Sup. Producao | E7: 30000
A8: CC-REPRO | B8: Reprocesso | C8: Produtivo (separado) | D8: Sup. Producao | E8: 4000
A9: CC-LAB | B9: Laboratorio/Qualidade | C9: Apoio | D9: Qualidade | E9: 6000
A10: CC-MANUT | B10: Manutencao | C10: Apoio | D10: Manutencao | E10: 8000
A12: ^ Linhas acima = dados DEMO (marcados). Abaixo: campos de entrada em branco para dados reais.

Sheet 14_ROUTINGS
A1: ROUTINGS
A2: Etapas: dosagem, mistura, transferencia, ensacamento, paletizacao, lab, movim., armazenag. Alimenta Time-Driven ABC (taxa x tempo consumido).
A4: Legenda: | B4: INPUT (editavel) | D4: FORMULA | F4: LINKED (de outra aba) | H4: CONTROL | J4: ALERT | L4: CHAVE/ID
A6: ROUTING_ID | B6: PRODUCT_ID | C6: Seq | D6: Etapa | E6: RESOURCE_ID | F6: Tempo padrao (h/t) | G6: Cap (t/h)
A7: RT-EXT | B7: P001 | C7: 1 | D7: Dosagem | E7: RES-MIST1 | F7: 0.06 | G7: 8
A8: RT-EXT | B8: P001 | C8: 2 | D8: Mistura | E8: RES-MIST1 | F8: 0.1 | G8: 6.5
A9: RT-EXT | B9: P001 | C9: 3 | D9: Ensacamento | E9: RES-MIST1 | F9: 0.05 | G9: 8
A10: RT-ARG | B10: P002 | C10: 1 | D10: Mistura | E10: RES-MIST1 | F10: 0.12 | G10: 6.5
A11: RT-REJ | B11: P003 | C11: 1 | D11: Mistura | E11: RES-MIST2 | F11: 0.16 | G11: 5
A13: ^ Linhas acima = dados DEMO (marcados). Abaixo: campos de entrada em branco para dados reais.

Sheet 19_LOSSES
A1: LOSSES
A2: Mass balance: entrada = bom + perda normal + perda anormal + reproc + WIP + nao explicado. Diferenca nao explicada (UNACCOUNTED) nunca e absorvida automaticamente.
A4: Legenda: | B4: INPUT (editavel) | D4: FORMULA | F4: LINKED (de outra aba) | H4: CONTROL | J4: ALERT | L4: CHAVE/ID
A6: OF_ID | B6: PRODUCT_ID | C6: Entrada MP (t) | D6: Bom (t) | E6: Perda normal (t) | F6: Perda anormal (t) | G6: Reproc (t) | H6: WIP (t) | I6: Nao explicado (t)
A7: OF-2603-01 | B7: P001 | C7: 402 | D7: 400 | E7: 2 | F7: 0 | G7: 0 | H7: 0 | I7: =C7-D7-E7-F7-G7-H7
A8: OF-2603-02 | B8: P002 | C8: 251 | D8: 250 | E8: 1 | F8: 0 | G8: 0 | H8: 0 | I8: =C8-D8-E8-F8-G8-H8
A9: OF-2603-03 | B9: P003 | C9: 121.5 | D9: 120 | E9: 1 | F9: 0 | G9: 0.5 | H9: 0 | I9: =C9-D9-E9-F9-G9-H9
A11: ^ Linhas acima = dados DEMO (marcados). Abaixo: campos de entrada em branco para dados reais.

Sheet 20_REPROCESS
A1: REPROCESS
A2: Excluir reproc dos indicadores da equipe principal; NAO excluir seu custo economico. Net Reprocess = custo perdido + recuperacao - valor recuperado.
A4: Legenda: | B4: INPUT (editavel) | D4: FORMULA | F4: LINKED (de outra aba) | H4: CONTROL | J4: ALERT | L4: CHAVE/ID
A6: REPRO_ID | B6: OF_ID origem | C6: PRODUCT_ID | D6: Qtd (t) | E6: Custo original perdido R$ | F6: Custo recuperacao R$ | G6: Valor recuperado R$ | H6: NET reprocess R$
A7: RP-001 | B7: OF-2603-03 | C7: P003 | D7: 0.5 | E7: 150 | F7: 60 | G7: 120 | H7: =E7+F7-G7
A9: ^ Linhas acima = dados DEMO (marcados). Abaixo: campos de entrada em branco para dados reais.

Sheet 21_ENERGY
A1: ENERGY
A2: Energy Price Variance e Energy Usage Variance. kWh/t por OF quando disponivel.
A4: Legenda: | B4: INPUT (editavel) | D4: FORMULA | F4: LINKED (de outra aba) | H4: CONTROL | J4: ALERT | L4: CHAVE/ID
A6: PERIOD | B6: RESOURCE_ID | C6: kWh consumidos | D6: Tarifa R$/kWh | E6: Demanda R$ | F6: Producao t | G6: kWh/t | H6: Custo energia R$
A7: 2026-03 | B7: RES-MIST1 | C7: 9000 | D7: 0.72 | E7: 1500 | F7: 650 | G7: =IFERROR(C7/F7,0) | H7: =C7*D7+E7
A9: ^ Linhas acima = dados DEMO (marcados). Abaixo: campos de entrada em branco para dados reais.

Sheet 22_LABOR
A1: LABOR
A2: Separar hora normal, extra, setup, espera, reprocesso, absenteismo. Labor Efficiency Variance.
A4: Legenda: | B4: INPUT (editavel) | D4: FORMULA | F4: LINKED (de outra aba) | H4: CONTROL | J4: ALERT | L4: CHAVE/ID
A6: PERIOD | B6: COST_CENTER_ID | C6: Horas normais | D6: Horas extras | E6: Taxa normal R$/h | F6: Taxa extra R$/h | G6: Horas padrao | H6: Custo MO R$
A7: 2026-03 | B7: CC-PROD | C7: 480 | D7: 40 | E7: 22 | F7: 33 | G7: 470 | H7: =C7*E7+D7*F7
A9: ^ Linhas acima = dados DEMO (marcados). Abaixo: campos de entrada em branco para dados reais.

Sheet 23_MAINTENANCE
A1: MAINTENANCE
A2: Maintenance Cost/Running Hour e Breakdown Economic Cost (inclui perda de producao).
A4: Legenda: | B4: INPUT (editavel) | D4: FORMULA | F4: LINKED (de outra aba) | H4: CONTROL | J4: ALERT | L4: CHAVE/ID
A6: PERIOD | B6: RESOURCE_ID | C6: Tipo | D6: Pecas R$ | E6: Servicos R$ | F6: Horas parada | G6: Perda producao R$ | H6: Custo total R$
A7: 2026-03 | B7: RES-MIST1 | C7: Corretiva | D7: 800 | E7: 400 | F7: 3 | G7: 900 | H7: =D7+E7+G7
A9: ^ Linhas acima = dados DEMO (marcados). Abaixo: campos de entrada em branco para dados reais.

Sheet 24_QUALITY
A1: QUALITY
A2: Prevention, Appraisal, Internal Failure, External Failure. Alimenta 11_COPQ / dashboards.
A4: Legenda: | B4: INPUT (editavel) | D4: FORMULA | F4: LINKED (de outra aba) | H4: CONTROL | J4: ALERT | L4: CHAVE/ID
A6: PERIOD | B6: PRODUCT_ID | C6: Classe | D6: Categoria | E6: Valor R$ | F6: Causa | G6: Responsavel area
A7: 2026-03 | B7: P003 | C7: Internal Failure | D7: Reprocesso | E7: 90 | F7: Ajuste cor | G7: Producao
A8: 2026-03 | B8: P001 | C8: Appraisal | D8: Ensaio lab | E8: 200 | F8: Controle rotina | G8: Qualidade
A10: ^ Linhas acima = dados DEMO (marcados). Abaixo: campos de entrada em branco para dados reais.

Sheet 25_INVENTORY
A1: INVENTORY
A2: Dias, giro, estoque medio + Inventory Carrying Cost (capital + armazenagem + seguro + obsoles.).
A4: Legenda: | B4: INPUT (editavel) | D4: FORMULA | F4: LINKED (de outra aba) | H4: CONTROL | J4: ALERT | L4: CHAVE/ID
A6: ITEM_ID | B6: Tipo | C6: Estoque medio R$ | D6: Dias | E6: Giro | F6: Armazenagem % | G6: Carrying cost R$
A7: M001 | B7: MP | C7: 64000 | D7: 30 | E7: 12 | F7: 0.03 | G7: =C7*(CUSTO_CAPITAL_ANO+F7)*D7/365
A8: P001 | B8: PA | C8: 30000 | D8: 15 | E8: 24 | F8: 0.03 | G8: =C8*(CUSTO_CAPITAL_ANO+F8)*D8/365
A10: ^ Linhas acima = dados DEMO (marcados). Abaixo: campos de entrada em branco para dados reais.

Sheet 30_CONSTRAINT
A1: CONSTRAINT
A2: Identifica o CONSTRAINT RESOURCE e a Margem de Contribuicao/hora do gargalo (mix, pedidos especiais).
A4: Legenda: | B4: INPUT (editavel) | D4: FORMULA | F4: LINKED (de outra aba) | H4: CONTROL | J4: ALERT | L4: CHAVE/ID
A6: RESOURCE_ID | B6: E gargalo? | C6: PRODUCT_ID | D6: MC unit R$/t | E6: Tempo gargalo h/t | F6: MC / hora gargalo R$
A7: RES-MIST1 | B7: Sim | C7: P001 | D7: 120 | E7: 0.21 | F7: =IFERROR(D7/E7,0)
A8: RES-MIST1 | B8: Sim | C8: P002 | D8: 140 | E8: 0.12 | F8: =IFERROR(D8/E8,0)
A10: ^ Linhas acima = dados DEMO (marcados). Abaixo: campos de entrada em branco para dados reais.

Sheet 33_SALES
A1: SALES
A2: Unidade minima de rentabilidade: CLIENTE x SKU.
A4: Legenda: | B4: INPUT (editavel) | D4: FORMULA | F4: LINKED (de outra aba) | H4: CONTROL | J4: ALERT | L4: CHAVE/ID
A6: SALE_ID | B6: CUSTOMER_ID | C6: PRODUCT_ID | D6: Data | E6: Qtd t | F6: Preco tabela R$/t | G6: Desconto R$/t | H6: Bonific R$/t | I6: Comissao % | J6: Prazo dias
A7: V-001 | B7: C001 | C7: P001 | D7: 2026-03-10 | E7: 20 | F7: 520 | G7: 10 | H7: 5 | I7: 0.02 | J7: 30
A8: V-002 | B8: C002 | C8: P002 | D8: 2026-03-11 | E8: 15 | F8: 560 | G8: 20 | H8: 0 | I8: 0.02 | J8: 45
A9: V-003 | B9: C003 | C9: P003 | D9: 2026-03-12 | E9: 5 | F9: 900 | G9: 0 | H9: 0 | I9: 0.03 | J9: 30
A11: ^ Linhas acima = dados DEMO (marcados). Abaixo: campos de entrada em branco para dados reais.

Sheet 34_FREIGHT_OUT
A1: FREIGHT OUT
A2: Frete absorvido entra no Cost to Serve e no Price Waterfall.
A4: Legenda: | B4: INPUT (editavel) | D4: FORMULA | F4: LINKED (de outra aba) | H4: CONTROL | J4: ALERT | L4: CHAVE/ID
A6: SALE_ID | B6: CUSTOMER_ID | C6: Frete total R$ | D6: Absorvido pela SKAL? | E6: R$/t
A7: V-001 | B7: C001 | C7: 800 | D7: Sim | E7: =IFERROR(C7/INDEX('33_SALES'!$E$7:$E$40,MATCH(A7,'33_SALES'!$A$7:$A$40,0)),0)
A9: ^ Linhas acima = dados DEMO (marcados). Abaixo: campos de entrada em branco para dados reais.

Sheet 35_COMMISSIONS
A1: COMMISSIONS
A2: Comissao por venda; entra no Cost to Serve.
A4: Legenda: | B4: INPUT (editavel) | D4: FORMULA | F4: LINKED (de outra aba) | H4: CONTROL | J4: ALERT | L4: CHAVE/ID
A6: SALE_ID | B6: Vendedor | C6: % comissao | D6: Base R$ | E6: Comissao R$
A7: V-001 | B7: Rep 1 | C7: 0.02 | D7: 7200 | E7: =C7*D7
A9: ^ Linhas acima = dados DEMO (marcados). Abaixo: campos de entrada em branco para dados reais.

Sheet 36_RECEIVABLES
A1: RECEIVABLES
A2: Receivable Financing Cost = valor x taxa x dias/365. Expected Credit Loss = PD x exposicao x LGD.
A4: Legenda: | B4: INPUT (editavel) | D4: FORMULA | F4: LINKED (de outra aba) | H4: CONTROL | J4: ALERT | L4: CHAVE/ID
A6: SALE_ID | B6: Valor a receber R$ | C6: Dias | D6: Custo prazo R$ | E6: PD % | F6: LGD % | G6: Expected credit loss R$
A7: V-001 | B7: 7000 | C7: 30 | D7: =B7*CUSTO_CAPITAL_ANO*C7/DIAS_ANO | E7: 0.015 | F7: 0.6 | G7: =B7*E7*F7
A9: ^ Linhas acima = dados DEMO (marcados). Abaixo: campos de entrada em branco para dados reais.

Sheet 37_BARTER
A1: BARTER
A2: Nao tratar permuta pelo valor nominal. Liquido = valor econom. - monetizacao - custo fin. - risco - trib.
A4: Legenda: | B4: INPUT (editavel) | D4: FORMULA | F4: LINKED (de outra aba) | H4: CONTROL | J4: ALERT | L4: CHAVE/ID
A6: BARTER_ID | B6: Contraparte | C6: Valor nominal R$ | D6: Valor economico R$ | E6: Custo monetizacao R$ | F6: Custo financeiro R$ | G6: Risco R$ | H6: Trib. adic R$ | I6: Liquido R$

Sheet 41_RECON_PHYSICAL
A1: RECON PHYSICAL
A2: Est. inicial + compras - consumo - perdas +/- transf = est. final esperado; comparar com real.
A4: Legenda: | B4: INPUT (editavel) | D4: FORMULA | F4: LINKED (de outra aba) | H4: CONTROL | J4: ALERT | L4: CHAVE/ID
A6: MATERIAL_ID | B6: Est. inicial t | C6: Compras t | D6: Consumo t | E6: Perdas t | F6: Transf t | G6: Est. final esperado t | H6: Est. final real t | I6: Diferenca t
A7: M001 | B7: 100 | C7: 30 | D7: 90.15 | E7: 0 | F7: 0 | G7: =B7+C7-D7-E7+F7 | H7: 39.85 | I7: =H7-G7
A9: ^ Linhas acima = dados DEMO (marcados). Abaixo: campos de entrada em branco para dados reais.

Sheet 31_COST_GAP
A1: COST GAP
A2: Actual -> Current Std -> Best Demonstrated -> Entitlement -> Theoretical. Controlavel/ano = (Actual - Entitlement) x volume anual. Amarelo = input (a preencher).
A4: Legenda: | B4: INPUT (editavel) | D4: FORMULA | F4: LINKED (de outra aba) | H4: CONTROL | J4: ALERT | L4: CHAVE/ID
A6: PRODUCT_ID | B6: 1.Actual R$/t | C6: 2.Frozen Std R$/t | D6: 3.Current Std R$/t | E6: 4.Replacement R$/t | F6: 5.Best Demonstr. R$/t | G6: 6.Entitlement R$/t | H6: 7.Theoretical R$/t | I6: Gap Act- CurStd | J6: Gap Act- Best | K6: Gap Act- Entitle | L6: Vol t/ano | M6: CONTROLAVEL R$/ano
A7: P001 | B7: =IFERROR(INDEX('27_ACTUAL_COST'!$H$7:$H$9,MATCH(A7,'27_ACTUAL_COST'!$A$7:$A$9,0)),0) | D7: =IFERROR(INDEX('26_STANDARD_COST'!$F$7:$F$9,MATCH(A7,'26_STANDARD_COST'!$A$7:$A$9,0)),0) | I7: =B7-D7 | J7: =IF(F7="","",B7-F7) | K7: =IF(G7="","",B7-G7) | M7: =IF(OR(G7="",L7=""),"",(B7-G7)*L7)
A8: P002 | B8: =IFERROR(INDEX('27_ACTUAL_COST'!$H$7:$H$9,MATCH(A8,'27_ACTUAL_COST'!$A$7:$A$9,0)),0) | D8: =IFERROR(INDEX('26_STANDARD_COST'!$F$7:$F$9,MATCH(A8,'26_STANDARD_COST'!$A$7:$A$9,0)),0) | I8: =B8-D8 | J8: =IF(F8="","",B8-F8) | K8: =IF(G8="","",B8-G8) | M8: =IF(OR(G8="",L8=""),"",(B8-G8)*L8)
A9: P003 | B9: =IFERROR(INDEX('27_ACTUAL_COST'!$H$7:$H$9,MATCH(A9,'27_ACTUAL_COST'!$A$7:$A$9,0)),0) | D9: =IFERROR(INDEX('26_STANDARD_COST'!$F$7:$F$9,MATCH(A9,'26_STANDARD_COST'!$A$7:$A$9,0)),0) | I9: =B9-D9 | J9: =IF(F9="","",B9-F9) | K9: =IF(G9="","",B9-G9) | M9: =IF(OR(G9="",L9=""),"",(B9-G9)*L9)
A11: Preencha Frozen Std, Replacement, Best Demonstrated, Entitlement, Theoretical e Volume (ver DATA_GAPS). Actual e Current Std sao calculados.

Sheet 32_SAVINGS
A1: SAVINGS
A2: 8 estagios: Identificado->Sustentado. So e REALIZADO com evidencia operacional E confirmacao financeira E reconciliacao (sem transferir custo, sem perder qualidade). Priority score = impacto x prob x velocidade / investimento.
A4: Legenda: | B4: INPUT (editavel) | D4: FORMULA | F4: LINKED (de outra aba) | H4: CONTROL | J4: ALERT | L4: CHAVE/ID
A6: SAVING_ID | B6: Causa | C6: Processo | D6: PRODUCT_ID | E6: Baseline R$/t | F6: Target R$/t | G6: Gap R$/t | H6: Volume t/ano | I6: Saving bruto R$/ano | J6: Investimento R$ | K6: Custo implem. R$ | L6: Saving liq. R$/ano | M6: Estagio (1-8) | N6: Evidencia oper.? | O6: Confirm. financ.? | P6: Realizado? | Q6: Priority score | R6: Responsavel | S6: Prazo
A7: SAV-001 | B7: Reduzir consumo cimento | C7: Formulacao | D7: P001 | E7: 160 | F7: 154 | G7: =E7-F7 | H7: 60000 | I7: =G7*H7 | J7: 5000 | K7: 2000 | L7: =I7-J7-K7 | M7: 3.Validado tec. | N7: Nao | O7: Nao | P7: =IF(AND(N7="Sim",O7="Sim"),"SIM","NAO") | Q7: =IFERROR(I7/1000*0.6*3/(J7/1000+1),0) | R7: Eng. Tecnico | S7: 2026-06-30
A8: SAV-002 | B8: Reduzir ociosidade MIST2 | C8: Producao | D8: P003 | E8: 58 | F8: 52 | G8: =E8-F8 | H8: 8000 | I8: =G8*H8 | J8: 0 | K8: 500 | L8: =I8-J8-K8 | M8: 2.Em analise | N8: Nao | O8: Nao | P8: =IF(AND(N8="Sim",O8="Sim"),"SIM","NAO") | Q8: =IFERROR(I8/1000*0.5*4/(J8/1000+1),0) | R8: Producao | S8: 2026-05-31
A10: ^ Linhas acima = dados DEMO (marcados). Abaixo: campos de entrada em branco para dados reais.

Sheet 38_COST_TO_SERVE
A1: COST TO SERVE
A2: Apos o custo industrial, agrega custos de servir por venda. Nota: no Pocket Price (40) os itens comerciais ja sao deduzidos; aqui e a visao consolidada do cost to serve.
A4: Legenda: | B4: INPUT (editavel) | D4: FORMULA | F4: LINKED (de outra aba) | H4: CONTROL | J4: ALERT | L4: CHAVE/ID
A6: SALE_ID | B6: PRODUCT_ID | C6: Qtd t | D6: Separacao R$ | E6: Carregamento R$ | F6: Frete R$ (link) | G6: Comissao R$ (link) | H6: Custo prazo R$ (link) | I6: Inadimpl R$ (link) | J6: Bonific/Devol R$ | K6: COST TO SERVE R$ | L6: R$/t
A7: V-001 | B7: P001 | C7: 20 | D7: 40 | E7: 60 | F7: =IFERROR(SUMIF('34_FREIGHT_OUT'!$A$7:$A$67,A7,'34_FREIGHT_OUT'!$C$7:$C$67),0) | G7: =IFERROR(SUMIF('35_COMMISSIONS'!$A$7:$A$67,A7,'35_COMMISSIONS'!$E$7:$E$67),0) | H7: =IFERROR(SUMIF('36_RECEIVABLES'!$A$7:$A$67,A7,'36_RECEIVABLES'!$D$7:$D$67),0) | I7: =IFERROR(SUMIF('36_RECEIVABLES'!$A$7:$A$67,A7,'36_RECEIVABLES'!$G$7:$G$67),0) | J7: 0 | K7: =SUM(D7:J7) | L7: =IFERROR(K7/C7,0)
A8: V-002 | B8: P002 | C8: 15 | D8: 30 | E8: 40 | F8: =IFERROR(SUMIF('34_FREIGHT_OUT'!$A$7:$A$67,A8,'34_FREIGHT_OUT'!$C$7:$C$67),0) | G8: =IFERROR(SUMIF('35_COMMISSIONS'!$A$7:$A$67,A8,'35_COMMISSIONS'!$E$7:$E$67),0) | H8: =IFERROR(SUMIF('36_RECEIVABLES'!$A$7:$A$67,A8,'36_RECEIVABLES'!$D$7:$D$67),0) | I8: =IFERROR(SUMIF('36_RECEIVABLES'!$A$7:$A$67,A8,'36_RECEIVABLES'!$G$7:$G$67),0) | J8: 0 | K8: =SUM(D8:J8) | L8: =IFERROR(K8/C8,0)
A9: V-003 | B9: P003 | C9: 5 | D9: 30 | E9: 40 | F9: =IFERROR(SUMIF('34_FREIGHT_OUT'!$A$7:$A$67,A9,'34_FREIGHT_OUT'!$C$7:$C$67),0) | G9: =IFERROR(SUMIF('35_COMMISSIONS'!$A$7:$A$67,A9,'35_COMMISSIONS'!$E$7:$E$67),0) | H9: =IFERROR(SUMIF('36_RECEIVABLES'!$A$7:$A$67,A9,'36_RECEIVABLES'!$D$7:$D$67),0) | I9: =IFERROR(SUMIF('36_RECEIVABLES'!$A$7:$A$67,A9,'36_RECEIVABLES'!$G$7:$G$67),0) | J9: 0 | K9: =SUM(D9:J9) | L9: =IFERROR(K9/C9,0)

Sheet 40_PROFITABILITY
A1: PROFITABILITY
A2: Price waterfall -> Pocket Price -> Pocket Margin. Custo industrial = custo real R$/t (27). Trib economica = pocket x ICMS efetivo. Verde = margem>0, vermelho = destruidor de valor.
A4: Legenda: | B4: INPUT (editavel) | D4: FORMULA | F4: LINKED (de outra aba) | H4: CONTROL | J4: ALERT | L4: CHAVE/ID
A6: SALE_ID | B6: CUST | C6: PROD | D6: Qtd t | E6: Preco tabela R$/t | F6: (-)Desc R$/t | G6: (-)Bonif R$/t | H6: (-)Comissao R$/t | I6: (-)Frete R$/t | J6: (-)Custo prazo R$/t | K6: (-)Inadimpl R$/t | L6: POCKET PRICE R$/t | M6: (-)Custo indl R$/t | N6: (-)C.serve extra R$/t | O6: (-)Trib econ R$/t | P6: POCKET MARGIN R$/t | Q6: Margem % | R6: Total R$ | S6: Flag
A7: V-001 | B7: =INDEX('33_SALES'!$B$7:$B$67,MATCH(A7,'33_SALES'!$A$7:$A$67,0)) | C7: =INDEX('33_SALES'!$C$7:$C$67,MATCH(A7,'33_SALES'!$A$7:$A$67,0)) | D7: =INDEX('33_SALES'!$E$7:$E$67,MATCH(A7,'33_SALES'!$A$7:$A$67,0)) | E7: =INDEX('33_SALES'!$F$7:$F$67,MATCH(A7,'33_SALES'!$A$7:$A$67,0)) | F7: =INDEX('33_SALES'!$G$7:$G$67,MATCH(A7,'33_SALES'!$A$7:$A$67,0)) | G7: =INDEX('33_SALES'!$H$7:$H$67,MATCH(A7,'33_SALES'!$A$7:$A$67,0)) | H7: =E7*INDEX('33_SALES'!$I$7:$I$67,MATCH(A7,'33_SALES'!$A$7:$A$67,0)) | I7: 40 | J7: =(E7-F7-G7)*CUSTO_CAPITAL_ANO*INDEX('33_SALES'!$J$7:$J$67,MATCH(A7,'33_SALES'!$A$7:$A$67,0))/DIAS_ANO | K7: =(E7-F7-G7)*INADIMPL_PCT | L7: =E7-F7-G7-H7-I7-J7-K7 | M7: =IFERROR(INDEX('27_ACTUAL_COST'!$H$7:$H$9,MATCH(C7,'27_ACTUAL_COST'!$A$7:$A$9,0)),0) | N7: 5 | O7: =L7*ICMS_EFETIVO | P7: =L7-M7-N7-O7 | Q7: =IFERROR(P7/E7,0) | R7: =P7*D7 | S7: =IF(P7<0,"DESTRUIDOR DE VALOR",IF(Q7<0.05,"MARGEM BAIXA","OK"))
A8: V-002 | B8: =INDEX('33_SALES'!$B$7:$B$67,MATCH(A8,'33_SALES'!$A$7:$A$67,0)) | C8: =INDEX('33_SALES'!$C$7:$C$67,MATCH(A8,'33_SALES'!$A$7:$A$67,0)) | D8: =INDEX('33_SALES'!$E$7:$E$67,MATCH(A8,'33_SALES'!$A$7:$A$67,0)) | E8: =INDEX('33_SALES'!$F$7:$F$67,MATCH(A8,'33_SALES'!$A$7:$A$67,0)) | F8: =INDEX('33_SALES'!$G$7:$G$67,MATCH(A8,'33_SALES'!$A$7:$A$67,0)) | G8: =INDEX('33_SALES'!$H$7:$H$67,MATCH(A8,'33_SALES'!$A$7:$A$67,0)) | H8: =E8*INDEX('33_SALES'!$I$7:$I$67,MATCH(A8,'33_SALES'!$A$7:$A$67,0)) | I8: 0 | J8: =(E8-F8-G8)*CUSTO_CAPITAL_ANO*INDEX('33_SALES'!$J$7:$J$67,MATCH(A8,'33_SALES'!$A$7:$A$67,0))/DIAS_ANO | K8: =(E8-F8-G8)*INADIMPL_PCT | L8: =E8-F8-G8-H8-I8-J8-K8 | M8: =IFERROR(INDEX('27_ACTUAL_COST'!$H$7:$H$9,MATCH(C8,'27_ACTUAL_COST'!$A$7:$A$9,0)),0) | N8: 5 | O8: =L8*ICMS_EFETIVO | P8: =L8-M8-N8-O8 | Q8: =IFERROR(P8/E8,0) | R8: =P8*D8 | S8: =IF(P8<0,"DESTRUIDOR DE VALOR",IF(Q8<0.05,"MARGEM BAIXA","OK"))
A9: V-003 | B9: =INDEX('33_SALES'!$B$7:$B$67,MATCH(A9,'33_SALES'!$A$7:$A$67,0)) | C9: =INDEX('33_SALES'!$C$7:$C$67,MATCH(A9,'33_SALES'!$A$7:$A$67,0)) | D9: =INDEX('33_SALES'!$E$7:$E$67,MATCH(A9,'33_SALES'!$A$7:$A$67,0)) | E9: =INDEX('33_SALES'!$F$7:$F$67,MATCH(A9,'33_SALES'!$A$7:$A$67,0)) | F9: =INDEX('33_SALES'!$G$7:$G$67,MATCH(A9,'33_SALES'!$A$7:$A$67,0)) | G9: =INDEX('33_SALES'!$H$7:$H$67,MATCH(A9,'33_SALES'!$A$7:$A$67,0)) | H9: =E9*INDEX('33_SALES'!$I$7:$I$67,MATCH(A9,'33_SALES'!$A$7:$A$67,0)) | I9: 0 | J9: =(E9-F9-G9)*CUSTO_CAPITAL_ANO*INDEX('33_SALES'!$J$7:$J$67,MATCH(A9,'33_SALES'!$A$7:$A$67,0))/DIAS_ANO | K9: =(E9-F9-G9)*INADIMPL_PCT | L9: =E9-F9-G9-H9-I9-J9-K9 | M9: =IFERROR(INDEX('27_ACTUAL_COST'!$H$7:$H$9,MATCH(C9,'27_ACTUAL_COST'!$A$7:$A$9,0)),0) | N9: 5 | O9: =L9*ICMS_EFETIVO | P9: =L9-M9-N9-O9 | Q9: =IFERROR(P9/E9,0) | R9: =P9*D9 | S9: =IF(P9<0,"DESTRUIDOR DE VALOR",IF(Q9<0.05,"MARGEM BAIXA","OK"))

Sheet 39_PRICING
A1: PRICING
A2: Cada nivel tem definicao matematica documentada. Caixa=custo incremental; Contribuicao=custo variavel; Equilibrio=custo total+servir; Min autorizado=equilibrio x(1+piso).
A4: Legenda: | B4: INPUT (editavel) | D4: FORMULA | F4: LINKED (de outra aba) | H4: CONTROL | J4: ALERT | L4: CHAVE/ID
A6: PRODUCT_ID | B6: Custo variavel R$/t | C6: Custo total R$/t | D6: Cost to serve medio R$/t | E6: Piso margem % | F6: 1.Preco caixa | G6: 2.Preco contrib. | H6: 3.Preco equilibrio | I6: 4.Preco min. autoriz. | J6: 5.Preco-alvo | K6: 6.Preco estrategico | L6: 7.Preco praticado
A7: P001 | B7: =IFERROR(INDEX('27_ACTUAL_COST'!$D$7:$D$9,MATCH(A7,'27_ACTUAL_COST'!$A$7:$A$9,0)),0) | C7: =IFERROR(INDEX('27_ACTUAL_COST'!$H$7:$H$9,MATCH(A7,'27_ACTUAL_COST'!$A$7:$A$9,0)),0) | D7: 5 | E7: 0.2 | F7: =B7 | G7: =B7 | H7: =C7+D7 | I7: =H7*(1+E7)
A8: P002 | B8: =IFERROR(INDEX('27_ACTUAL_COST'!$D$7:$D$9,MATCH(A8,'27_ACTUAL_COST'!$A$7:$A$9,0)),0) | C8: =IFERROR(INDEX('27_ACTUAL_COST'!$H$7:$H$9,MATCH(A8,'27_ACTUAL_COST'!$A$7:$A$9,0)),0) | D8: 5 | E8: 0.2 | F8: =B8 | G8: =B8 | H8: =C8+D8 | I8: =H8*(1+E8)
A9: P003 | B9: =IFERROR(INDEX('27_ACTUAL_COST'!$D$7:$D$9,MATCH(A9,'27_ACTUAL_COST'!$A$7:$A$9,0)),0) | C9: =IFERROR(INDEX('27_ACTUAL_COST'!$H$7:$H$9,MATCH(A9,'27_ACTUAL_COST'!$A$7:$A$9,0)),0) | D9: 5 | E9: 0.2 | F9: =B9 | G9: =B9 | H9: =C9+D9 | I9: =H9*(1+E9)

Sheet 42_RECON_COST
A1: RECON COST
A2: Para cada produto: Custo padrao + variacoes = custo real. Residual deve -> 0. Se residual !=0, ha variacao nao identificada (nunca esconder em 'Outros').
A4: Legenda: | B4: INPUT (editavel) | D4: FORMULA | F4: LINKED (de outra aba) | H4: CONTROL | J4: ALERT | L4: CHAVE/ID
A6: PRODUCT_ID | B6: Std total R$ (26!G) | C6: PPV R$ | D6: Usage R$ | E6: Conv var R$ | F6: Total var R$ | G6: Std+Var R$ | H6: Actual R$ (27!G) | I6: Residual R$
A7: P001 | B7: =IFERROR(INDEX('26_STANDARD_COST'!$G$7:$G$9,MATCH(A7,'26_STANDARD_COST'!$A$7:$A$9,0)),0) | C7: =IFERROR(INDEX('28_VARIANCES'!$D$23:$D$25,MATCH(A7,'28_VARIANCES'!$A$23:$A$25,0)),0) | D7: =IFERROR(INDEX('28_VARIANCES'!$E$23:$E$25,MATCH(A7,'28_VARIANCES'!$A$23:$A$25,0)),0) | E7: =IFERROR(INDEX('28_VARIANCES'!$K$23:$K$25,MATCH(A7,'28_VARIANCES'!$A$23:$A$25,0)),0) | F7: =C7+D7+E7 | G7: =B7+F7 | H7: =IFERROR(INDEX('27_ACTUAL_COST'!$G$7:$G$9,MATCH(A7,'27_ACTUAL_COST'!$A$7:$A$9,0)),0) | I7: =ROUND(G7-H7,2)
A8: P002 | B8: =IFERROR(INDEX('26_STANDARD_COST'!$G$7:$G$9,MATCH(A8,'26_STANDARD_COST'!$A$7:$A$9,0)),0) | C8: =IFERROR(INDEX('28_VARIANCES'!$D$23:$D$25,MATCH(A8,'28_VARIANCES'!$A$23:$A$25,0)),0) | D8: =IFERROR(INDEX('28_VARIANCES'!$E$23:$E$25,MATCH(A8,'28_VARIANCES'!$A$23:$A$25,0)),0) | E8: =IFERROR(INDEX('28_VARIANCES'!$K$23:$K$25,MATCH(A8,'28_VARIANCES'!$A$23:$A$25,0)),0) | F8: =C8+D8+E8 | G8: =B8+F8 | H8: =IFERROR(INDEX('27_ACTUAL_COST'!$G$7:$G$9,MATCH(A8,'27_ACTUAL_COST'!$A$7:$A$9,0)),0) | I8: =ROUND(G8-H8,2)
A9: P003 | B9: =IFERROR(INDEX('26_STANDARD_COST'!$G$7:$G$9,MATCH(A9,'26_STANDARD_COST'!$A$7:$A$9,0)),0) | C9: =IFERROR(INDEX('28_VARIANCES'!$D$23:$D$25,MATCH(A9,'28_VARIANCES'!$A$23:$A$25,0)),0) | D9: =IFERROR(INDEX('28_VARIANCES'!$E$23:$E$25,MATCH(A9,'28_VARIANCES'!$A$23:$A$25,0)),0) | E9: =IFERROR(INDEX('28_VARIANCES'!$K$23:$K$25,MATCH(A9,'28_VARIANCES'!$A$23:$A$25,0)),0) | F9: =C9+D9+E9 | G9: =B9+F9 | H9: =IFERROR(INDEX('27_ACTUAL_COST'!$G$7:$G$9,MATCH(A9,'27_ACTUAL_COST'!$A$7:$A$9,0)),0) | I9: =ROUND(G9-H9,2)
A11: Residual total: | I11: =ROUND(SUM(I7:I9),2)

Sheet 43_RECON_ACCOUNTING
A1: RECON ACCOUNTING
A2: Bridge entre COST MODEL e RAZAO/CPV: contas, centros, estoque, provisoes, depreciacao, competencia, rateios. Sem driver causal defensavel -> UNALLOCATED (nao ratear).
A4: Legenda: | B4: INPUT (editavel) | D4: FORMULA | F4: LINKED (de outra aba) | H4: CONTROL | J4: ALERT | L4: CHAVE/ID
A6: Conta contabil | B6: Centro custo | C6: Cost model R$ | D6: Razao/CPV R$ | E6: Diferenca R$ | F6: Natureza da diferenca
A7: Materias-primas consumidas | B7: CC-PROD | E7: =C7-D7 | F7: Competencia/estoque
A8: Mao de obra direta | B8: CC-PROD | E8: =C8-D8 | F8: Rateio/provisao
A9: Energia | B9: CC-PROD | E9: =C9-D9 | F9: Competencia
A10: Depreciacao | B10: CC-PROD | E10: =C10-D10 | F10: Metodo
A11: Manutencao | B11: CC-MANUT | E11: =C11-D11 | F11: Provisao
A12: UNALLOCATED (sem driver) | B12: - | E12: =C12-D12 | F12: Custo nao alocado por falta de driver
A14: ^ Linhas acima = dados DEMO (marcados). Abaixo: campos de entrada em branco para dados reais.

Sheet 44_EXEC_DASHBOARD
A1: PAINEL EXECUTIVO — SKAL COST INTELLIGENCE
A2: Poucos numeros, alto impacto. Todos os valores sao calculados das abas de origem. R$/ton boa produzida como unidade base.
B4: CUSTO REAL R$/t | D4: CUSTO PADRAO R$/t | F4: COST GAP TOTAL R$
B5: =IFERROR(SUM('27_ACTUAL_COST'!$G$7:$G$9)/SUM('17_PRODUCTION_OF'!$L$7:$L$47),0) | D5: =IFERROR(SUM('26_STANDARD_COST'!$G$7:$G$9)/SUM('17_PRODUCTION_OF'!$L$7:$L$47),0) | F5: =SUM('27_ACTUAL_COST'!$G$7:$G$9)-SUM('26_STANDARD_COST'!$G$7:$G$9)
B7: COST GAP R$/t | D7: SAVINGS REALIZADOS R$ | F7: SAVINGS PIPELINE R$
B8: =IFERROR((SUM('27_ACTUAL_COST'!$G$7:$G$9)-SUM('26_STANDARD_COST'!$G$7:$G$9))/SUM('17_PRODUCTION_OF'!$L$7:$L$47),0) | D8: =SUMIF('32_SAVINGS'!$P$7:$P$67,"SIM",'32_SAVINGS'!$L$7:$L$67) | F8: =SUMIF('32_SAVINGS'!$P$7:$P$67,"NAO",'32_SAVINGS'!$L$7:$L$67)
B10: UNUSED CAPACITY R$ | D10: COPQ R$ | F10: GOOD TONS
B11: =SUM('29_CAPACITY'!$F$7:$F$8) | D11: =SUM('24_QUALITY'!$E$7:$E$67) | F11: =SUM('17_PRODUCTION_OF'!$L$7:$L$47)
B14: DECOMPOSICAO DO DESVIO (Actual - Standard) — R$
B15: Componente | C15: R$ | D15: % do gap
B16: PPV (preco de compra) | C16: =SUM('28_VARIANCES'!$D$23:$D$25) | D16: =IFERROR(C16/(SUM('27_ACTUAL_COST'!$G$7:$G$9)-SUM('26_STANDARD_COST'!$G$7:$G$9)),0)
B17: Usage (consumo) | C17: =SUM('28_VARIANCES'!$E$23:$E$25) | D17: =IFERROR(C17/(SUM('27_ACTUAL_COST'!$G$7:$G$9)-SUM('26_STANDARD_COST'!$G$7:$G$9)),0)
B18: - Mix | C18: =SUM('28_VARIANCES'!$J$23:$J$25) | D18: =IFERROR(C18/(SUM('27_ACTUAL_COST'!$G$7:$G$9)-SUM('26_STANDARD_COST'!$G$7:$G$9)),0)
B19: - Yield | C19: =SUM('28_VARIANCES'!$I$23:$I$25) | D19: =IFERROR(C19/(SUM('27_ACTUAL_COST'!$G$7:$G$9)-SUM('26_STANDARD_COST'!$G$7:$G$9)),0)
B20: Conversao | C20: =SUM('28_VARIANCES'!$K$23:$K$25) | D20: =IFERROR(C20/(SUM('27_ACTUAL_COST'!$G$7:$G$9)-SUM('26_STANDARD_COST'!$G$7:$G$9)),0)
B21: TOTAL (PPV+Usage+Conversao) | C21: =SUM('28_VARIANCES'!$D$23:$D$25)+SUM('28_VARIANCES'!$E$23:$E$25)+SUM('28_VARIANCES'!$K$23:$K$25) | D21: =IFERROR(C21/(SUM('27_ACTUAL_COST'!$G$7:$G$9)-SUM('26_STANDARD_COST'!$G$7:$G$9)),0)
B23: Nota: PPV+Usage+Conversao deve igualar o Cost Gap Total (Actual-Standard). Ver 42_RECON_COST (residual -> 0).

Sheet 45_PRODUCTION_DASHBOARD
A1: PRODUCTION DASHBOARD
A2: Produtividade, yield, perdas, energia, COPQ, custo controlavel.
B4: Metrica | C4: Valor | D4: Fonte
B5: Good tons (mes) | C5: =SUM('17_PRODUCTION_OF'!$L$7:$L$47) | D5: 17_PRODUCTION_OF
B6: t/h medio (RES-MIST1) | C6: =IFERROR(SUMIF('17_PRODUCTION_OF'!$E$7:$E$47,"RES-MIST1",'17_PRODUCTION_OF'!$L$7:$L$47)/SUMIF('17_PRODUCTION_OF'!$E$7:$E$47,"RES-MIST1",'17_PRODUCTION_OF'!$Q$7:$Q$47),0) | D6: 17
B7: Perda total (t) | C7: =SUM('17_PRODUCTION_OF'!$O$7:$O$47) | D7: 17
B8: Nao explicado (t) | C8: =SUM('19_LOSSES'!$I$7:$I$67) | D8: 19_LOSSES
B9: Usage variance R$ | C9: =SUM('28_VARIANCES'!$E$23:$E$25) | D9: 28
B10: Yield variance R$ | C10: =SUM('28_VARIANCES'!$I$23:$I$25) | D10: 28
B11: Energia R$/t | C11: =IFERROR(SUM('21_ENERGY'!$H$7:$H$67)/SUM('17_PRODUCTION_OF'!$L$7:$L$47),0) | D11: 21_ENERGY
B12: COPQ R$ | C12: =SUM('24_QUALITY'!$E$7:$E$67) | D12: 24_QUALITY
B13: Unused capacity R$ | C13: =SUM('29_CAPACITY'!$F$7:$F$8) | D13: 29_CAPACITY

Sheet 46_PROCUREMENT_DASHBOARD
A1: PROCUREMENT DASHBOARD
A2: PPV, landed cost, TCO, should cost, supplier gap, credito tributario.
B4: Metrica | C4: Valor | D4: Fonte
B5: PPV total R$ | C5: =SUM('28_VARIANCES'!$D$23:$D$25) | D5: 28
B6: Landed net Cimento R$/t | C6: =IFERROR(INDEX('09_LANDED_COST'!$P$7:$P$47,MATCH("M001",'09_LANDED_COST'!$A$7:$A$47,0)),0) | D6: 09
B7: Credito tributario potencial R$ | C7: =SUM('11_TAX_CREDITS'!$D$7:$D$67)+SUM('11_TAX_CREDITS'!$E$7:$E$67) | D7: 11_TAX_CREDITS
B8: Should cost gap R$ | C8: DADO NECESSARIO | D8: 16 (DATA_GAPS: preco mercado/should cost)
B9: Supplier TCO ranking | C9: DADO NECESSARIO | D9: 15/TCO (DATA_GAPS)

Sheet 47_COMMERCIAL_DASHBOARD
A1: COMMERCIAL DASHBOARD
A2: Preco, pocket price, cost to serve, margem, cliente x SKU. O comercial NAO altera formulas de custo industrial.
B4: Metrica | C4: Valor | D4: Fonte
B5: Pocket margin total R$ | C5: =SUM('40_PROFITABILITY'!$R$7:$R$9) | D5: 40_PROFITABILITY
B6: Cost to serve total R$ | C6: =SUM('38_COST_TO_SERVE'!$K$7:$K$67) | D6: 38
B7: Vendas total t | C7: =SUM('33_SALES'!$E$7:$E$67) | D7: 33_SALES
B8: Destruidores de valor (qtd) | C8: =COUNTIF('40_PROFITABILITY'!$S$7:$S$9,"DESTRUIDOR DE VALOR") | D8: 40
B9: Inadimplencia esperada R$ | C9: =SUM('36_RECEIVABLES'!$G$7:$G$67) | D9: 36

Sheet 48_COST_REDUCTION_DASHBOARD
A1: COST REDUCTION DASHBOARD
A2: Potencial identificado -> validado -> implementado -> realizado -> sustentado.
B4: Metrica | C4: Valor | D4: Fonte
B5: Saving bruto (pipeline) R$/ano | C5: =SUM('32_SAVINGS'!$I$7:$I$67) | D5: 32_SAVINGS
B6: Saving liquido (pipeline) R$/ano | C6: =SUM('32_SAVINGS'!$L$7:$L$67) | D6: 32
B7: Saving REALIZADO R$ | C7: =SUMIF('32_SAVINGS'!$P$7:$P$67,"SIM",'32_SAVINGS'!$L$7:$L$67) | D7: 32 (regra: evidencia+financeiro)
B8: Cost gap controlavel R$/ano | C8: =SUMIF('31_COST_GAP'!$M$7:$M$9,"<>") | D8: 31_COST_GAP
B9: Top priority score | C9: =IFERROR(MAX('32_SAVINGS'!$Q$7:$Q$67),0) | D9: 32

Sheet DATA_DICTIONARY
A1: DICTIONARY
A2: Nenhum campo ambiguo. Chaves unicas nunca dependem apenas da descricao textual.
A4: Legenda: | B4: INPUT (editavel) | D4: FORMULA | F4: LINKED (de outra aba) | H4: CONTROL | J4: ALERT | L4: CHAVE/ID
A6: Campo | B6: Tabela/Aba | C6: Tipo | D6: Unidade | E6: Obrigatorio | F6: Fonte | G6: Definicao
A7: PRODUCT_ID | B7: 03_PRODUCTS | C7: texto | D7: - | E7: Sim | F7: Cadastro | G7: Chave unica do produto (SKU)
A8: MATERIAL_ID | B8: 04_MATERIALS | C8: texto | D8: - | E8: Sim | F8: Cadastro | G8: Chave unica da materia-prima
A9: Extras? | B9: 03_PRODUCTS | C9: bool | D9: - | E9: Sim | F9: Producao | G9: TRUE -> 20kg/saco,75/palete; FALSE -> 15/100
A10: kg/t produto | B10: 06_BOM | C10: numero | D10: kg/t | E10: Sim | F10: Tecnico | G10: Quantidade padrao de MP por tonelada de produto
A11: LANDED NET R$/t | B11: 09_LANDED_COST | C11: numero | D11: R$/t | E11: Sim | F11: Compras/Fiscal | G11: Custo liquido posto fabrica por tonelada
A12: Good tons | B12: 17_PRODUCTION_OF | C12: numero | D12: t | E12: Sim | F12: Producao | G12: Toneladas boas liberadas (base de todos os R$/t)
A13: Act kg/t | B13: 18_ACTUAL_CONSUMPTION | C13: numero | D13: kg/t | E13: Sim | F13: Producao | G13: Consumo real por tonelada boa
A14: PPV | B14: 28_VARIANCES | C14: numero | D14: R$ | E14: Calc | F14: Sistema | G14: (Preco real - padrao) x qtd real
A15: Usage Variance | B15: 28_VARIANCES | C15: numero | D15: R$ | E15: Calc | F15: Sistema | G15: (Qtd real - padrao permitida) x preco padrao
A16: Pocket Price | B16: 40_PROFITABILITY | C16: numero | D16: R$/t | E16: Calc | F16: Sistema | G16: Preco liquido de bolso (waterfall)
A17: Saving liquido | B17: 32_SAVINGS | C17: numero | D17: R$/ano | E17: Calc | F17: Sistema | G17: Saving bruto - investimento - custo implementacao
A18: ICMS_EFETIVO | B18: 01_CONTROL_PANEL | C18: numero | D18: % | E18: Sim | F18: Fiscal | G18: ICMS nominal x % efetivamente devido (benef. 80%)
A20: ^ Linhas acima = dados DEMO (marcados). Abaixo: campos de entrada em branco para dados reais.

Sheet DATA_GAPS
A1: GAPS
A2: Cada linha e um campo de entrada ja criado no sistema, aguardando dado real. Prioridade por R$ de impacto anual (ver 01_CONTROL_PANEL materialidade).
A4: Legenda: | B4: INPUT (editavel) | D4: FORMULA | F4: LINKED (de outra aba) | H4: CONTROL | J4: ALERT | L4: CHAVE/ID
A6: Informacao faltante | B6: Impacto | C6: Responsavel | D6: Prioridade | E6: Finalidade | F6: Formato necessario
A7: Planilha_Precificacao.xlsx (arquivo legado) | B7: Sem ela nao ha reconciliacao com o modelo atual (LEGACY_RECON) | C7: Controladoria | D7: ALTA | E7: Mapear precos/formulas atuais | F7: .xlsx
A8: CustoFormula2026.1.xlsb | B8: Estrutura detalhada de custos atual | C8: Controladoria | D8: ALTA | E8: Reconciliacao e validacao | F8: .xlsb
A9: Landed cost real das MP de PRODUCAO (areia/aditivos) | B9: Cimento/calcario ja reais (R3); faltam demais MP | C9: Compras/Fiscal | D9: ALTA | E9: R3_LANDED_REAL / 09 | F9: Itens NF por MP
A10: Frete inbound do calcario e demais MP | B10: Landed do calcario incompleto (so cimento tem frete) | C10: Compras/Log. | D10: MEDIA | E10: R3_LANDED_REAL | F10: CT-e por carga
A11: Vinculo NF-item x OF de producao | B11: Ligar compra real ao consumo/BOM | C11: Producao/Compras | D11: ALTA | E11: R2 -> 18 | F11: Chave OF
A12: kWh por equipamento | B12: Energia/t estimada | C12: Producao | D12: ALTA | E12: 21_ENERGY | F12: kWh por OF/recurso
A13: Preco historico por fornecedor | B13: PPV / should cost incompletos | C13: Compras | D13: ALTA | E13: 10/PPV | F13: Serie temporal
A14: Perda e reprocesso por OF | B14: Yield e mass balance incompletos | C14: Producao | D14: ALTA | E14: 17/19/20 | F14: Por OF
A15: Tempos reais de inicio/fim por lote/traco | B15: Produtividade real (t/h) por OF | C15: Producao | D15: ALTA | E15: 17_PRODUCTION_OF | F15: hh:mm por OF
A16: Custos fixos por recurso (dep/manut/MO) | B16: R$/hora e unused capacity | C16: Controladoria | D16: MEDIA | E16: 12/15/29 | F16: R$/mes por recurso
A17: Entitlement / best demonstrated / theoretical | B17: Cost gap completo | C17: Eng./Controladoria | D17: MEDIA | E17: 31_COST_GAP | F17: R$/t por SKU
... A23: Aliquotas reforma (CBS/IBS) por ano | B23: Cenarios 2026-2033 | C23: Fiscal | D23: MEDIA | E23: 10_TAX_RULES | F23: % por vigencia
A25: ^ Linhas acima = dados DEMO (marcados). Abaixo: campos de entrada em branco para dados reais.

Sheet LEGACY_RECON
A1: RECON
A2: Comparacao produto a produto. Legado (amarelo) vem da Planilha_Precificacao.xlsx (ver DATA_GAPS). Novo custo industrial e calculado (27_ACTUAL_COST).
A4: Legenda: | B4: INPUT (editavel) | D4: FORMULA | F4: LINKED (de outra aba) | H4: CONTROL | J4: ALERT | L4: CHAVE/ID
A6: PRODUCT_ID | B6: Preco atual (legado) | C6: Custo atual (legado) | D6: Novo custo industrial R$/t | E6: Novo custo economico R$/t | F6: Dif. abs. R$/t | G6: Dif. % | H6: Causa da diferenca
A7: P001 | D7: =IFERROR(INDEX('27_ACTUAL_COST'!$H$7:$H$9,MATCH(A7,'27_ACTUAL_COST'!$A$7:$A$9,0)),0) | E7: =D7 | F7: =IF(C7="","",D7-C7) | G7: =IF(C7="","",IFERROR((D7-C7)/C7,0))
A8: P002 | D8: =IFERROR(INDEX('27_ACTUAL_COST'!$H$7:$H$9,MATCH(A8,'27_ACTUAL_COST'!$A$7:$A$9,0)),0) | E8: =D8 | F8: =IF(C8="","",D8-C8) | G8: =IF(C8="","",IFERROR((D8-C8)/C8,0))
A9: P003 | D9: =IFERROR(INDEX('27_ACTUAL_COST'!$H$7:$H$9,MATCH(A9,'27_ACTUAL_COST'!$A$7:$A$9,0)),0) | E9: =D9 | F9: =IF(C9="","",D9-C9) | G9: =IF(C9="","",IFERROR((D9-C9)/C9,0))
A11: Preencha as colunas do legado ao receber Planilha_Precificacao.xlsx. Causas tipicas: divergencia de metodologia, premissa sem suporte, dado nao rastreavel.

Sheet CONTROLS_ALERTS
A1: CONTROLES E ALERTAS AUTOMATICOS
A2: Verde = OK, Vermelho = investigar. Estes testes implementam a aceitacao do modelo (BOM fecha, Std+Var=Actual, sem custo negativo, etc.).
B4: Verificacao | C4: Status | D4: Regra
B5: BOM fecha (soma kg/t = 1000) — P001 | C5: =IF(ABS(SUMIF('06_BOM'!$A$7:$A$67,"P001",'06_BOM'!$E$7:$E$67)-1000)<=1,"OK","ALERTA") | D5: Fechamento fisico da formulacao
B6: BOM fecha — P002 | C6: =IF(ABS(SUMIF('06_BOM'!$A$7:$A$67,"P002",'06_BOM'!$E$7:$E$67)-1000)<=1,"OK","ALERTA") | D6: Fechamento fisico
B7: BOM fecha — P003 | C7: =IF(ABS(SUMIF('06_BOM'!$A$7:$A$67,"P003",'06_BOM'!$E$7:$E$67)-1000)<=1,"OK","ALERTA") | D7: Fechamento fisico
B8: Reconciliacao Std+Var=Actual (residual total) | C8: =IF(ABS(SUM('28_VARIANCES'!$N$7:$N$18))<0.01,"OK","ALERTA") | D8: Residual por linha -> 0
B9: Reconciliacao por produto (42_RECON_COST) | C9: =IF(ABS(SUM('42_RECON_COST'!$I$7:$I$9))<0.01,"OK","ALERTA") | D9: Std total + var = Actual
B10: Sem custo real negativo | C10: =IF(MIN('27_ACTUAL_COST'!$H$7:$H$9)>=0,"OK","ALERTA") | D10: Custo/t nao pode ser negativo
B11: Material sem landed cost (custo zero no BOM) | C11: =IF(SUMPRODUCT(('06_BOM'!$E$7:$E$67>0)*('06_BOM'!$K$7:$K$67=0))=0,"OK","ALERTA") | D11: Toda MP usada deve ter custo rastreavel
B12: Perda nao explicada (mass balance) | C12: =IF(SUM('19_LOSSES'!$I$7:$I$67)<=0.5,"OK","ALERTA") | D12: Unaccounted loss nao absorvida
B13: Produtos destruidores de valor | C13: =IF(COUNTIF('40_PROFITABILITY'!$S$7:$S$9,"DESTRUIDOR DE VALOR")=0,"OK","ALERTA") | D13: Pocket margin < 0
B14: ICMS efetivo consistente (nominal x devido) | C14: =IF(ABS(ICMS_EFETIVO-ICMS_NOMINAL*(1-ICMS_REDUCAO))<0.0001,"OK","ALERTA") | D14: Sem hardcode de 4,5%
B16: TESTES DE ACEITACAO (98): rastreabilidade de MP, BOM fecha, OF reconcilia, Std+Var=Actual, ponte contabil, sem alocacao sem driver, fonte+responsavel, preco decomponivel ate custo, saving reconciliavel, leitura em segundos.

Sheet R0_DADOS_REAIS
A1: DADOS REAIS — COMPRAS (NOTAS DE ENTRADA)
A2: Fonte: 2026-01 (SKAL_Compras_2026-01_Extracao.xlsx), 2026-08 (SKAL_Compras_2026-08_Extracao.xlsx). Itens sem quantidade/valor legiveis no OCR foram descartados (nunca inferidos). Estes numeros SAO reais, ao contrario do dataset DEMO.
B4: Arquivos ingeridos | C4: 2
B5: Fornecedores (dedup CNPJ) | C5: 81
B6: Gasto total mapeado (R$) | C6: 1341012.2
B7: Itens de produto legiveis | C7: 6
B8: Documentos no ledger | C8: 154
B9: CT-e de frete | C9: 31
B10: Registros de energia | C10: 5
B12: ACHADO-CHAVE | E12: O frete inbound do cimento (Apodi/CE -> Teresina/PI) e um driver de custo de primeira ordem: ver R3_LANDED_REAL.

Sheet R1_FORNECEDORES_REAL
A1: FORNECEDORES REAIS
A2: Fonte: 2026-01 (SKAL_Compras_2026-01_Extracao.xlsx), 2026-08 (SKAL_Compras_2026-08_Extracao.xlsx) Gasto = soma dos documentos (ledger R4), agregado por CNPJ.
A3: CNPJ | B3: Razao social | C3: UF | D3: Regime | E3: Gasto total R$ | F3: Meses
B4: COMPANHIA INDUSTRIAL DE CIMENTO APODI | C4: CE | E4: 353381.45 | F4: 2026-01, 2026-08
B5: F G INTELIGENCIA EM LOGISTICA LTDA | C5: CE | E5: 343917.6 | F5: 2026-01, 2026-08
B6: FENIX PRESTADORA DE SERVICOS LTDA | C6: PI | D6: ME ou EPP optante pelo Simples Nacional | E6: 69350 | F6: 2026-01, 2026-08
B7: PLASTER DISTRIBUIDORA LTDA | E7: 43536 | F7: 2026-01
B8: G R DE MORAES CONSTRUCOES | E8: 40000 | F8: 2026-01
B9: E & P SOARES DOS SANTOS LTDA - ME | E9: 35238.7 | F9: 2026-01
B10: VALORTOIICA MEERA) —_TOLABES.CACIGTES 3) DEAS. RCANDICLOANDO (RH GUNE DE CHIEUL DO MEGN RS) ALLY. (HK) VALOR DO HOON RS) | E10: 35238.7 | F10: 2026-01
B11: POLI-GYN EMBALAGENS LTDA | E11: 32443.09 | F11: 2026-01
B12: JUVENCIO REPRESENTACOES LIMITADA | E12: 31325.86 | F12: 2026-01
B13: RENOVAR INDUSTRIA E COMERCIO DE EMBALAGENS EIRELI | E13: 29892.54 | F13: 2026-01
B14: INOVE SOLUCOES EM PRODUTOS E EQUIPAMENTOS PARA LABORATORIOS | E14: 27000 | F14: 2026-01
B15: EQUATORIAL PIAUI DISTRIBUIDORA DE ENERGIA S.A. | E15: 24691.95 | F15: 2026-01
A16: 02.950.057/0001-87 | B16: JOSIMAR INOCENCIO DE MORAIS - ME | C16: CE | D16: Não optante pelo Simples | E16: 16600 | F16: 2026-08
B17: ‘AORDE SANTEE ESCORT CONLONADE DEVCON CETERA (SON FEDO | E17: 15662.93 | F17: 2026-01
B18: KLESIO KENNEDY REPRESENTACAO DE MATERIAL DE CONSTRUCAO LTDA | E18: 14933 | F18: 2026-01
B19: FRANCISCO DAS CHAGAS BISPO DE ARAUJO JUNIOR | E19: 14800 | F19: 2026-01
B20: JORGE GUILHERME COSTA FERREIRA | C20: PI | D20: MEI / Simples Nacional | E20: 14500 | F20: 2026-01, 2026-08
B21: F J DE SOUSA REPRESENTACOES | E21: 14232.77 | F21: 2026-01
B22: EDWARD MOURA SOCIEDADE INDIVIDUAL DE ADVOCACIA | C22: PI | D22: ME ou EPP optante pelo Simples Nacional | E22: 12225 | F22: 2026-01, 2026-08
B23: LCM CONSULTING AND INFORMATION SERVICES LTDA | E23: 11478.08 | F23: 2026-01
A24: 17.858.631/0001-49 | B24: MATRIX COMERCIALIZADORA DE ENERGIA ELETRICA S/A | C24: SP | E24: 10128.08 | F24: 2026-08
B25: TELEVISAO PIONEIRA LTDA | E25: 10000 | F25: 2026-01
B26: CONSULTING AND INFORMATION SERVICES LTOA | E26: 9689.93 | F26: 2026-01
B27: EVERARDO SILVA DO NASCIMENTO | E27: 8238 | F27: 2026-01
B28: FIXENGIODO 650M STAGE DO PREETADOR DO SANI PERA O SIMELENHECISNM EIN COPIA DO BIBWIGBE DO OS | E28: 8175 | F28: 2026-01
B29: DALZEDOREDEENISABO — COMPETTINCTS = MIMOROFÉRIT ‘SSEENAC SA OS POND | E29: 8175 | F29: 2026-01
B30: ATHOS MED SERVICOS EM SAUDE - LTDA | E30: 5922 | F30: 2026-01
B31: HOSPITAIS E CLINICAS DO PIAUI S/S LTDA | E31: 5901.18 | F31: 2026-01
B32: CAIEIRA CANTA GALO EXTRACAO E COMERCIO DE CALCARIO LTDA | E32: 4880 | F32: 2026-01
B33: MICHELA MEDEIROS FRANCO | E33: 4800 | F33: 2026-01
B34: GRACILENE MARIA BEZERRA DOS SANTOS | E34: 4782.92 | F34: 2026-01
B35: EMERSON CANDIDO DE AQUINO 56476779320 | E35: 4500 | F35: 2026-01
B36: JESUINO@APOIOCONTABILP.COM | E36: 4198 | F36: 2026-01
A37: 07.776.339/0002-04 | B37: CALCARIO CANTA GALO EXTRACAO E COMERCIO DE CALCARIO LTDA | C37: CE | E37: 4035 | F37: 2026-08
B38: LOCAL DA PRESZAGDO DO SARVIGO AIA DA PRECTAGSO DO SERVIGO | E38: 4000 | F38: 2026-01
A39: 28.399.452/0001-07 | B39: VALDIR RIBEIRO DE MELO ME | C39: PI | D39: ME ou EPP optante pelo Simples Nacional | E39: 3750 | F39: 2026-08
A40: 48.714.053/0001-09 | B40: MOACIR GONCALVES PALMEIRA JUNIOR | C40: PI | D40: MEI / Simples Nacional | E40: 3681 | F40: 2026-08
A41: 49.765.012/0001-04 | B41: CLAUDIANE DE ARAUJO MENDES CIPRIANO | C41: PI | D41: MEI / Simples Nacional | E41: 3675.13 | F41: 2026-08
B42: DISTRIBUIDORA DE BEBIDAS ATACADAO DA GELA | E42: 3600 | F42: 2026-01
B43: J E SILVA LIMA - ME | E43: 3258 | F43: 2026-01
B44: MARCEL DE MOURA GOMES LTDA | E44: 3000 | F44: 2026-01
B45: SACK EXPLORACAO DE SALOES DE FESTAS, CENTRO DE CONVENCOES, ESCRITORIOS VIRTUNS. STANDS, QUADRAS ESPORTIVAS,ESTADIOS, GNASIOS, | E45: 3000 | F45: 2026-01
B46: J K B FIALHO LTDA | E46: 3000 | F46: 2026-01
B47: CONNECT INFORMACOES E TECNOLOGIA SA | C47: DF | E47: 2961.88 | F47: 2026-01, 2026-08
B48: BOA VISTA AUTO ELETRICA LTDA | E48: 2111 | F48: 2026-01
B49: CACIQUE PNEUS INDUSTRIA E COMERCIO LTDA | E49: 2104.68 | F49: 2026-01
B50: JAILSON DA CONCEICAO PAIVA | E50: 2000 | F50: 2026-01
B51: APODI DISTRIBUICAO E LOGISTICA LTDA | E51: 1820 | F51: 2026-01
B52: INTERMEDIARIO DO SERVIC NAO IDENTIACADO NA NFE'S. | E52: 1708.72 | F52: 2026-01
B53: INDUMAK MAQUINAS LTDA | E53: 1587.23 | F53: 2026-01
B54: GESTAO - INOVACAO EMPRESARIAL LTDA | E54: 1518 | F54: 2026-01
B55: NATUS AMBIENTAL LTDA | E55: 1516.1 | F55: 2026-01
B56: MILMAQ METALURGICA E MANUTENCAO INDUSTRIAL LTDA - ME | E56: 1500 | F56: 2026-01
B57: A LUIZ NETO LTDA | E57: 1500 | F57: 2026-01
A58: 63.865.191/0001-74 | B58: DUO OPERACOES PROTOS LTDA | C58: PI | D58: Optante pelo Simples Nacional | E58: 1300 | F58: 2026-08
B59: AUTO SHOP RASTREAMENTO LTDA | E59: 1198 | F59: 2026-01
B60: ELITE PECAS E MAQUINAS LTDA | E60: 1016.4 | F60: 2026-01
B61: MARCOS JOSE FONTANA HANUS | E61: 932 | F61: 2026-01
B62: AREA CONTRIBUTENTE: MENSAGENS PRIORITARIAS / AVISOS AO CONSUMIDOR . | E62: 900 | F62: 2026-01
B63: BORGES & CAMURCA RESTAURANTES LTDA | E63: 819 | F63: 2026-01
B64: DISTRIBUICAO DE ALIMENTOS VANGUARDA S/A | E64: 800 | F64: 2026-01
B65: - REPRESENTANTES COMERCIAIS E AGENTES DO COMERGIO DE MADEIRA, MATERIAL DE CONSTRUCAO E FERRAGENS, | E65: 797.56 | F65: 2026-01
B66: F. ALVES CAMINHA - ME | E66: 797.56 | F66: 2026-01
B67: MINERAR ENGENHARIA E MEIO AMBIENTE LTDA | E67: 759 | F67: 2026-01
A68: 08.877.746/0001-90 | B68: K F DA S B LEMOS - ME | C68: PI | D68: ME ou EPP optante pelo Simples Nacional | E68: 756.27 | F68: 2026-08
B69: R F DAS B LEMOS - ME | E69: 751.47 | F69: 2026-01
B70: BEER WO REVES ORO MOO PAROLE MHRUNZOUDRAMLOTE AAR MEAL TREEAPRORASE OA077.60 | E70: 751.47 | F70: 2026-01
B71: LENCO CENTRO DE CONTROLE TECNOLOGICO LTDA | E71: 750 | F71: 2026-01
B72: TRANS VNC TRANSPORTES EIRELI | E72: 703 | F72: 2026-01
B73: MARINA NAYARA FLORES GUIMARAES - ME | E73: 480 | F73: 2026-01
A74: 18.787.111/0001-55 | B74: AGUIA EXPRESS RH PRESTADORA DE SERVICOS EIRELI EPP | C74: CE | D74: Não optante pelo Simples na data de competência | E74: 450 | F74: 2026-08
B75: TICKET LOG / EDENRED SOLUCOES INSTITUICAO DE PAGAMENTO HA S.A. | E75: 358.58 | F75: 2026-01
B76: ROMILSON SILVA DE ASSIS | E76: 350 | F76: 2026-01
B77: DUO TELECOM LTDA | E77: 300 | F77: 2026-01
B78: VANGUARD PECAS E SERVICOS AUTOMOTIVOS LTDA | E78: 270 | F78: 2026-01
B79: PAZ & SAMPAIO LTDA - MM LOCACOES | E79: 265 | F79: 2026-01
B80: J R C DE ANDRADES LTDA | E80: 139.9 | F80: 2026-01
B81: M H F SANTOS AUTOPECAS | E81: 120 | F81: 2026-01
B82: ERENDR SHO RNCRCO MOM SAND EXTREMA FENCES I ARAGL SRARES80 | E82: 75 | F82: 2026-01
B83: TERRA NOVA (LOT. MECO 16459, SAO SEBASTIAO. | E83: 7.5 | F83: 2026-01
B84: F'OE0 522 MICHELA MEDEIROS FRANCO MICHELAMEDEIROBZ3€2GMAILCOM | E84: 0 | F84: 2026-01
D85: TOTAL | E85: =SUM(E4:E84)

Sheet R2_COMPRAS_REAIS
A1: COMPRAS REAIS POR ITEM
A2: Fonte: 2026-01 (SKAL_Compras_2026-01_Extracao.xlsx), 2026-08 (SKAL_Compras_2026-08_Extracao.xlsx) Somente itens com quantidade e valor unitario numericos.
A3: Mes | B3: Doc | C3: Descricao | D3: NCM | E3: Un | F3: Qtd | G3: Valor unit. R$ | H3: Valor total R$ | I3: Emitente
A4: 2026-08 | B4: D005 | C4: ENERGIA ELETRICA | D4: 27160000 | E4: MWH | F4: 27.59 | G4: 280.31 | H4: 7733.75 | I4: MATRIX COMERCIALIZADORA DE ENERGIA ELETRICA S/A
A5: 2026-08 | B5: D011 | C5: CIMENTO PORTLAND - CP V ARI | D5: 25232910 | E5: T | F5: 37.97 | G5: 505 | H5: 19174.85 | I5: COMPANHIA INDUSTRIAL DE CIMENTO APODI
A6: 2026-08 | B6: D012 | C6: CIMENTO PORTLAND - CP V ARI | D6: 25232910 | E6: T | F6: 37.69 | G6: 505 | H6: 19033.45 | I6: COMPANHIA INDUSTRIAL DE CIMENTO APODI
A7: 2026-08 | B7: D017 | C7: CIMENTO PORTLAND - CP V ARI | D7: 25232910 | E7: T | F7: 0.08 | G7: 505 | H7: 40.4 | I7: COMPANHIA INDUSTRIAL DE CIMENTO APODI
A8: 2026-08 | B8: D017 | C8: CIMENTO PORTLAND - CP V ARI | D8: 25232910 | E8: T | F8: 38 | G8: 505 | H8: 19190 | I8: COMPANHIA INDUSTRIAL DE CIMENTO APODI
A9: 2026-08 | B9: D018 | C9: CALCARIO DOLOMITICO #170 (SACOS 25 KG) | D9: 25181000 | E9: T | F9: 15 | G9: 269 | H9: 4035 | I9: CALCARIO CANTA GALO EXTRACAO E COMERCIO DE CALCARIO LTDA

Sheet R3_LANDED_REAL
A1: LANDED COST REAL — AGOSTO 2026
A2: Preco de NF NAO e custo. O frete inbound entra no custo posto fabrica. Cimento CST 500 = ICMS por substituicao (sem credito na entrada).
B4: Material | C4: Qtd (t) | D4: NF R$/t | E4: Frete R$/t | F4: LANDED R$/t | G4: % frete s/ NF
B5: Cimento CP-V ARI (Apodi) | C5: 113.74 | D5: 505 | E5: 330 | F5: =D5+E5 | G5: =IFERROR(E5/D5,0)
B6: Calcario dolomitico #170 | C6: 15 | D6: 269 | F6: =D6+IF(E6="",0,E6) | G6: =IFERROR(IF(E6="",0,E6)/D6,0)
B8: Frete cimento total (Apodi, ago): R$ 37534.20 em 113 t => R$ 330.00/t
B9: Leitura: a NF do cimento e R$505/t, mas o LANDED e ~R$835/t. O frete inbound adiciona ~65% ao custo. Calcario: confirmar frete (DATA_GAPS).

Sheet R4_NOTAS_LEDGER
A1: NOTAS DE ENTRADA — LEDGER
A2: Fonte: 2026-01 (SKAL_Compras_2026-01_Extracao.xlsx), 2026-08 (SKAL_Compras_2026-08_Extracao.xlsx) Nivel documento (Tributos_por_Doc): valor e ICMS por nota.
A3: Mes | B3: Doc | C3: Tipo | D3: Numero | E3: Unidade | F3: Emitente | G3: CNPJ | H3: Valor doc R$ | I3: Aliq ICMS | J3: ICMS R$
A4: 2026-01 | B4: JAN26-P001 | C4: Energia/NF3e | D4: 67912850 | F4: EQUATORIAL PIAUI DISTRIBUIDORA DE ENERGIA S.A. | H4: 23789.49 | I4: 0.225 | J4: 4892.56
A5: 2026-01 | B5: JAN26-P003 | C5: Energia/NF3e | D5: 67620505 | F5: EQUATORIAL PIAUI DISTRIBUIDORA DE ENERGIA S.A. | H5: 29.6 | J5: 0
A6: 2026-01 | B6: JAN26-P004 | C6: Energia/NF3e | D6: 67003437 | F6: EQUATORIAL PIAUI DISTRIBUIDORA DE ENERGIA S.A. | H6: 29.78 | J6: 0
A7: 2026-01 | B7: JAN26-P005 | C7: Energia/NF3e | D7: 67888805 | F7: EQUATORIAL PIAUI DISTRIBUIDORA DE ENERGIA S.A. | H7: 843.08 | I7: 0.225 | J7: 174.11
A8: 2026-01 | B8: JAN26-P012 | C8: NFS-e | D8: 863 | F8: GESTAO - INOVACAO EMPRESARIAL LTDA | H8: 759
A9: 2026-01 | B9: JAN26-P013 | C9: NFS-e | D9: 863 | F9: GESTAO - INOVACAO EMPRESARIAL LTDA | H9: 759
A10: 2026-01 | B10: JAN26-P014 | C10: NFCom | D10: 303 | F10: TELEVISAO PIONEIRA LTDA | H10: 10000 | J10: 0
A11: 2026-01 | B11: JAN26-P017 | C11: CT-e | D11: 446 | F11: F G INTELIGENCIA EM LOGISTICA LTDA | H11: 11702.5 | I11: 0.12 | J11: 1404.3
A12: 2026-01 | B12: JAN26-P018 | C12: CT-e | D12: 445 | F12: F G INTELIGENCIA EM LOGISTICA LTDA | H12: 11838.9 | I12: 0.12 | J12: 1420.67
A13: 2026-01 | B13: JAN26-P019 | C13: CT-e | D13: 443 | F13: F G INTELIGENCIA EM LOGISTICA LTDA | H13: 11789.3 | I13: 0.12 | J13: 1414.72
A14: 2026-01 | B14: JAN26-P022 | C14: NF-e | D14: 537098 | F14: COMPANHIA INDUSTRIAL DE CIMENTO APODI | H14: 18686.25 | I14: 0.12 | J14: 2242.35
A15: 2026-01 | B15: JAN26-P023 | C15: NF-e | D15: 536966 | F15: COMPANHIA INDUSTRIAL DE CIMENTO APODI | H15: 18904.05 | I15: 0.12 | J15: 2268.49
A16: 2026-01 | B16: JAN26-P024 | C16: NF-e | D16: 536748 | F16: COMPANHIA INDUSTRIAL DE CIMENTO APODI | H16: 18824.85 | I16: 0.12 | J16: 2258.98
A17: 2026-01 | B17: JAN26-P025 | C17: CT-e | F17: TRANS VNC TRANSPORTES EIRELI | H17: 703 | I17: 0.12 | J17: 49.21
A18: 2026-01 | B18: JAN26-P028 | C18: NFS-e | F18: TERRA NOVA (LOT. MECO 16459, SAO SEBASTIAO. | H18: 7.5
A19: 2026-01 | B19: JAN26-P030 | C19: NFS-e | F19: JESUINO@APOIOCONTABILP.COM | H19: 4198
A20: 2026-01 | B20: JAN26-P031 | C20: NFS-e | D20: 5 | F20: - REPRESENTANTES COMERCIAIS E AGENTES DO COMERGIO DE MADEIRA, MATERIAL DE CONSTRUCAO E FERRAGENS, | H20: 797.56
A21: 2026-01 | B21: JAN26-P035 | C21: NFS-e | D21: 0 | F21: CONSULTING AND INFORMATION SERVICES LTOA | H21: 9689.93
A22: 2026-01 | B22: JAN26-P039 | C22: NFS-e | F22: AUTO SHOP RASTREAMENTO LTDA | H22: 1198
A23: 2026-01 | B23: JAN26-P041 | C23: NF-e | D23: 536564 | F23: COMPANHIA INDUSTRIAL DE CIMENTO APODI | H23: 17790.3 | I23: 0.12 | J23: 2134.84
A24: 2026-01 | B24: JAN26-P042 | C24: NF-e | D24: 536357 | F24: COMPANHIA INDUSTRIAL DE CIMENTO APODI | H24: 18607.05 | I24: 0.12 | J24: 2232.85
A25: 2026-01 | B25: JAN26-P043 | C25: NF-e | D25: 536302 | F25: COMPANHIA INDUSTRIAL DE CIMENTO APODI | H25: 18711 | I25: 0.12 | J25: 2245.32
A26: 2026-01 | B26: JAN26-P044 | C26: NF-e | D26: 536108 | F26: COMPANHIA INDUSTRIAL DE CIMENTO APODI | H26: 18814.95 | I26: 0.12 | J26: 2257.79
A27: 2026-01 | B27: JAN26-P045 | C27: NF-e | D27: 535954 | F27: COMPANHIA INDUSTRIAL DE CIMENTO APODI | H27: 18621.9 | I27: 0.12 | J27: 2234.63
A28: 2026-01 | B28: JAN26-P046 | C28: NF-e | D28: 535509 | F28: COMPANHIA INDUSTRIAL DE CIMENTO APODI | H28: 18839.7 | I28: 0.12 | J28: 2260.76
A29: 2026-01 | B29: JAN26-P047 | C29: CT-e | D29: 438 | F29: F G INTELIGENCIA EM LOGISTICA LTDA | H29: 11141.4 | I29: 0.12 | J29: 1336.97
A30: 2026-01 | B30: JAN26-P048 | C30: CT-e | D30: 433 | F30: F G INTELIGENCIA EM LOGISTICA LTDA | H30: 11652.9 | I30: 0.12 | J30: 1398.35
A31: 2026-01 | B31: JAN26-P049 | C31: CT-e | D31: 431 | F31: F G INTELIGENCIA EM LOGISTICA LTDA | H31: 11718 | I31: 0.12 | J31: 1406.16
A32: 2026-01 | B32: JAN26-P050 | C32: CT-e | D32: 426 | F32: F G INTELIGENCIA EM LOGISTICA LTDA | H32: 11783.1 | I32: 0.12 | J32: 1413.97
A33: 2026-01 | B33: JAN26-P051 | C33: CT-e | D33: 421 | F33: F G INTELIGENCIA EM LOGISTICA LTDA | H33: 11662.2 | I33: 0.12 | J33: 1399.46
A34: 2026-01 | B34: JAN26-P052 | C34: CT-e | D34: 418 | F34: F G INTELIGENCIA EM LOGISTICA LTDA | H34: 11798.6 | I34: 0.12 | J34: 1415.83
... A36: 2026-01 | B36: JAN26-P054 | C36: NF-e | D36: 2181 | F36: CAIEIRA CANTA GALO EXTRACAO E COMERCIO DE CALCARIO LTDA | H36: 4392 | I36: 0.12 | J36: 232.74
A37: 2026-01 | B37: JAN26-P055 | C37: NF-e | D37: 17232 | F37: PLASTER DISTRIBUIDORA LTDA | H37: 43536 | J37: 5059.87
A38: 2026-01 | B38: JAN26-P056 | C38: NFS-e | D38: 27 | F38: JAILSON DA CONCEICAO PAIVA | H38: 2000
A39: 2026-01 | B39: JAN26-P057 | C39: NFS-e | D39: 24 | F39: EMERSON CANDIDO DE AQUINO 56476779320 | H39: 2500
A40: 2026-01 | B40: JAN26-P058 | C40: NFS-e | D40: 960441 | F40: HOSPITAIS E CLINICAS DO PIAUI S/S LTDA | H40: 5901.18
A41: 2026-01 | B41: JAN26-P059 | C41: NF-e | D41: 832 | F41: ROMILSON SILVA DE ASSIS | H41: 350
A42: 2026-01 | B42: JAN26-P060 | C42: NFS-e | D42: 36 | F42: MARCOS JOSE FONTANA HANUS | H42: 52
A43: 2026-01 | B43: JAN26-P061 | C43: NFS-e | D43: 330 | F43: MINERAR ENGENHARIA E MEIO AMBIENTE LTDA | H43: 759
A44: 2026-01 | B44: JAN26-P062 | C44: NFS-e | D44: 53 | F44: KLESIO KENNEDY REPRESENTACAO DE MATERIAL DE CONSTRUCAO LTDA | H44: 14933
A45: 2026-01 | B45: JAN26-P063 | C45: NFS-e | D45: 244 | F45: F. ALVES CAMINHA - ME | H45: 797.56
A46: 2026-01 | B46: JAN26-P064 | C46: NFS-e | D46: 221 | F46: E & P SOARES DOS SANTOS LTDA - ME | H46: 35238.7
A47: 2026-01 | B47: JAN26-P065 | C47: NFS-e | D47: 57 | F47: F J DE SOUSA REPRESENTACOES | H47: 14232.77
A48: 2026-01 | B48: JAN26-P066 | C48: NFS-e | D48: 32 | F48: GRACILENE MARIA BEZERRA DOS SANTOS | H48: 4782.92
A49: 2026-01 | B49: JAN26-P069 | C49: NFS-e | D49: 4 | F49: JUVENCIO REPRESENTACOES LIMITADA | H49: 15662.93
A50: 2026-01 | B50: JAN26-P070 | C50: NFS-e | D50: 3 | F50: JUVENCIO REPRESENTACOES LIMITADA | H50: 15662.93
A51: 2026-01 | B51: JAN26-P077 | C51: NF-e | D51: 535011 | F51: COMPANHIA INDUSTRIAL DE CIMENTO APODI | H51: 15797.5 | I51: 0.12 | J51: 1895.7
A52: 2026-01 | B52: JAN26-P078 | C52: NF-e | D52: 861 | F52: INOVE SOLUCOES EM PRODUTOS E EQUIPAMENTOS PARA LABORATORIOS | H52: 27000
A53: 2026-01 | B53: JAN26-P080 | C53: NFCom | D53: 5011 | F53: J R C DE ANDRADES LTDA | H53: 139.9 | J53: 0
A54: 2026-01 | B54: JAN26-P081 | C54: NF-e | D54: 60587 | F54: DISTRIBUICAO DE ALIMENTOS VANGUARDA S/A | H54: 800
A55: 2026-01 | B55: JAN26-P082 | C55: NFS-e | D55: 767 | F55: EDWARD MOURA SOCIEDADE INDIVIDUAL DE ADVOCACIA | H55: 4075
A56: 2026-01 | B56: JAN26-P083 | C56: NFS-e | D56: 3331 | F56: LCM CONSULTING AND INFORMATION SERVICES LTDA | H56: 9689.33
A57: 2026-01 | B57: JAN26-P084 | C57: NF-e | D57: 232676 | F57: INDUMAK MAQUINAS LTDA | H57: 1587.23 | J57: 100.51
A58: 2026-01 | B58: JAN26-P087 | C58: CT-e | D58: 409 | F58: F G INTELIGENCIA EM LOGISTICA LTDA | H58: 11683.9 | I58: 0.12 | J58: 1402.07
A59: 2026-01 | B59: JAN26-P088 | C59: CT-e | D59: 408 | F59: F G INTELIGENCIA EM LOGISTICA LTDA | H59: 11776.9 | I59: 0.12 | J59: 1413.23
A60: 2026-01 | B60: JAN26-P089 | C60: CT-e | D60: 407 | F60: F G INTELIGENCIA EM LOGISTICA LTDA | H60: 2307.5 | I60: 0.12 | J60: 276.9
A61: 2026-01 | B61: JAN26-P090 | C61: CT-e | D61: 405 | F61: F G INTELIGENCIA EM LOGISTICA LTDA | H61: 11711.8 | I61: 0.12 | J61: 1405.42
A62: 2026-01 | B62: JAN26-P091 | C62: CT-e | D62: 401 | F62: F G INTELIGENCIA EM LOGISTICA LTDA | H62: 11764.5 | I62: 0.12 | J62: 1411.74
A63: 2026-01 | B63: JAN26-P092 | C63: NF-e | D63: 535504 | F63: COMPANHIA INDUSTRIAL DE CIMENTO APODI | H63: 18676.35 | I63: 0.12 | J63: 2241.16
A64: 2026-01 | B64: JAN26-P093 | C64: NF-e | D64: 535252 | F64: COMPANHIA INDUSTRIAL DE CIMENTO APODI | H64: 18720.9 | I64: 0.12 | J64: 2246.51
A65: 2026-01 | B65: JAN26-P094 | C65: NF-e | D65: 535128 | F65: COMPANHIA INDUSTRIAL DE CIMENTO APODI | H65: 18656.55 | I65: 0.12 | J65: 2238.79
A66: 2026-01 | B66: JAN26-P096 | C66: NF-e | D66: 534870 | F66: COMPANHIA INDUSTRIAL DE CIMENTO APODI | H66: 18701.1 | I66: 0.12 | J66: 2244.13
A67: 2026-01 | B67: JAN26-P097 | C67: NF-e | D67: 534761 | F67: COMPANHIA INDUSTRIAL DE CIMENTO APODI | H67: 18785.25 | I67: 0.12 | J67: 2254.23
A68: 2026-01 | B68: JAN26-P098 | C68: CT-e | D68: 373 | F68: F G INTELIGENCIA EM LOGISTICA LTDA | H68: 11795.5 | I68: 0.12 | J68: 1415.46
A69: 2026-01 | B69: JAN26-P100 | C69: CT-e | D69: 376 | F69: F G INTELIGENCIA EM LOGISTICA LTDA | H69: 11687 | I69: 0.12 | J69: 1402.44
... A73: 2026-01 | B73: JAN26-P108 | C73: CT-e | D73: 389 | F73: F G INTELIGENCIA EM LOGISTICA LTDA | H73: 11612.6 | I73: 0.12 | J73: 1393.51
A74: 2026-01 | B74: JAN26-P111 | C74: NFS-e | D74: 536943 | F74: CONNECT INFORMACOES E TECNOLOGIA SA | H74: 460
A75: 2026-01 | B75: JAN26-P112 | C75: NF-e | D75: 402080 | F75: APODI DISTRIBUICAO E LOGISTICA LTDA | H75: 1820
A76: 2026-01 | B76: JAN26-P113 | C76: NFS-e | D76: 22 | F76: JORGE GUILHERME COSTA FERREIRA | H76: 500
A77: 2026-01 | B77: JAN26-P114 | C77: NF-e | D77: 20113 | F77: DISTRIBUIDORA DE BEBIDAS ATACADAO DA GELA | H77: 3600
A78: 2026-01 | B78: JAN26-P116 | C78: NF-e | D78: 172 | F78: EVERARDO SILVA DO NASCIMENTO | H78: 8238
A79: 2026-01 | B79: JAN26-P117 | C79: CT-e | D79: 417 | F79: F G INTELIGENCIA EM LOGISTICA LTDA | H79: 11696.3 | I79: 0.12 | J79: 1403.56
A80: 2026-01 | B80: JAN26-P118 | C80: CT-e | D80: 411 | F80: F G INTELIGENCIA EM LOGISTICA LTDA | H80: 11724.2 | I80: 0.12 | J80: 1406.9
A81: 2026-01 | B81: JAN26-P119 | C81: NF-e | D81: 77338 | F81: POLI-GYN EMBALAGENS LTDA | H81: 32443.09 | J81: 1182.44
A82: 2026-01 | B82: JAN26-P120 | C82: NF-e | D82: 535055 | F82: COMPANHIA INDUSTRIAL DE CIMENTO APODI | H82: 18805.05 | I82: 0.12 | J82: 2256.61
A83: 2026-01 | B83: JAN26-P121 | C83: CT-e | D83: 392 | F83: F G INTELIGENCIA EM LOGISTICA LTDA | H83: 11625 | I83: 0.12 | J83: 1395
A84: 2026-01 | B84: JAN26-P123 | C84: CT-e | D84: 393 | F84: F G INTELIGENCIA EM LOGISTICA LTDA | H84: 11770.7 | I84: 0.12 | J84: 1412.48
A85: 2026-01 | B85: JAN26-P126 | C85: CT-e | D85: 394 | F85: F G INTELIGENCIA EM LOGISTICA LTDA | H85: 11745.9 | I85: 0.12 | J85: 1409.51
A86: 2026-01 | B86: JAN26-P128 | C86: CT-e | D86: 396 | F86: F G INTELIGENCIA EM LOGISTICA LTDA | H86: 11804.8 | I86: 0.12 | J86: 1416.58
A87: 2026-01 | B87: JAN26-P129 | C87: CT-e | D87: 397 | F87: F G INTELIGENCIA EM LOGISTICA LTDA | H87: 11699.4 | I87: 0.12 | J87: 1403.93
A88: 2026-01 | B88: JAN26-P130 | C88: Fatura/Locacao | D88: 003260 | F88: PAZ & SAMPAIO LTDA - MM LOCACOES | H88: 265
A89: 2026-01 | B89: JAN26-P131 | C89: NFS-e | D89: 167 | F89: FENIX PRESTADORA DE SERVICOS LTDA | H89: 8175
A90: 2026-01 | B90: JAN26-P132 | C90: NFS-e | D90: 166 | F90: FENIX PRESTADORA DE SERVICOS LTDA | H90: 8175
A91: 2026-01 | B91: JAN26-P133 | C91: NFS-e | D91: 22 | F91: EMERSON CANDIDO DE AQUINO 56476779320 | H91: 2000
A92: 2026-01 | B92: JAN26-P134 | C92: NFS-e | D92: 767 | F92: EDWARD MOURA SOCIEDADE INDIVIDUAL DE ADVOCACIA | H92: 4075
A93: 2026-01 | B93: JAN26-P135 | C93: NFS-e | D93: 16004 | F93: LENCO CENTRO DE CONTROLE TECNOLOGICO LTDA | H93: 750
A94: 2026-01 | B94: JAN26-P136 | C94: NFS-e | D94: 3320 | F94: LCM CONSULTING AND INFORMATION SERVICES LTDA | H94: 1788.75
A95: 2026-01 | B95: JAN26-P143 | C95: NFS-e | D95: 3 | F95: MICHELA MEDEIROS FRANCO | H95: 4800
A96: 2026-01 | B96: JAN26-P144 | C96: NFS-e | D96: 18513 | F96: VANGUARD PECAS E SERVICOS AUTOMOTIVOS LTDA | H96: 270
A97: 2026-01 | B97: JAN26-P145 | C97: NFS-e | D97: 9 | F97: MARCEL DE MOURA GOMES LTDA | H97: 3000
A98: 2026-01 | B98: JAN26-P146 | C98: Fatura/Reembolso | D98: 67178532 | F98: TICKET LOG / EDENRED SOLUCOES INSTITUICAO DE PAGAMENTO HA S.A. | H98: 358.58
A99: 2026-01 | B99: JAN26-P147 | C99: NF-e | D99: 3520 | F99: BORGES & CAMURCA RESTAURANTES LTDA | H99: 819
A100: 2026-01 | B100: JAN26-P148 | C100: NF-e | D100: 16028 | F100: RENOVAR INDUSTRIA E COMERCIO DE EMBALAGENS EIRELI | H100: 29892.54 | J100: 3268.43
A101: 2026-01 | B101: JAN26-P149 | C101: NFCom | D101: 213 | F101: DUO TELECOM LTDA | H101: 300 | J101: 0
A102: 2026-01 | B102: JAN26-P150 | C102: NF-e | D102: 4834 | F102: ELITE PECAS E MAQUINAS LTDA | H102: 1016.4 | J102: 61.6
A103: 2026-01 | B103: JAN26-P153 | C103: NFS-e | D103: 221 | F103: VALORTOIICA MEERA) —_TOLABES.CACIGTES 3) DEAS. RCANDICLOANDO (RH GUNE DE CHIEUL DO MEGN RS) ALLY. (HK) VALOR DO HOON RS) | H103: 35238.7
A104: 2026-01 | B104: JAN26-P154 | C104: NFS-e | D104: 3992/U | F104: R F DAS B LEMOS - ME | H104: 751.47
...

Sheet R5_FRETES_CTE
A1: FRETES INBOUND (CT-e)
A2: Fonte: 2026-01 (SKAL_Compras_2026-01_Extracao.xlsx), 2026-08 (SKAL_Compras_2026-08_Extracao.xlsx)
A3: Mes | B3: CT-e | C3: Transportadora | D3: Origem | E3: Destino | F3: Remetente | G3: Valor R$
A4: 2026-01 | B4: 446 | C4: F G INTELIGENCIA EM LOGISTICA LTDA | F4: COMPANHIA INDUSTRIAL DE CIMENTO APODI | G4: 11702.5
A5: 2026-01 | B5: 445 | C5: F G INTELIGENCIA EM LOGISTICA LTDA | F5: COMPANHIA INDUSTRIAL DE CIMENTO APODI | G5: 11838.9
A6: 2026-01 | B6: 443 | C6: F G INTELIGENCIA EM LOGISTICA LTDA | F6: COMPANHIA INDUSTRIAL DE CIMENTO APODI | G6: 11789.3
A7: 2026-01 | C7: TRANS VNC TRANSPORTES EIRELI | G7: 703
A8: 2026-01 | B8: 438 | C8: F G INTELIGENCIA EM LOGISTICA LTDA | F8: COMPANHIA INDUSTRIAL DE CIMENTO APODI | G8: 11141.4
A9: 2026-01 | B9: 433 | C9: F G INTELIGENCIA EM LOGISTICA LTDA | F9: COMPANHIA INDUSTRIAL DE CIMENTO APODI | G9: 11652.9
A10: 2026-01 | B10: 431 | C10: F G INTELIGENCIA EM LOGISTICA LTDA | F10: COMPANHIA INDUSTRIAL DE CIMENTO APODI | G10: 11718
A11: 2026-01 | B11: 426 | C11: F G INTELIGENCIA EM LOGISTICA LTDA | F11: COMPANHIA INDUSTRIAL DE CIMENTO APODI | G11: 11783.1
A12: 2026-01 | B12: 421 | C12: F G INTELIGENCIA EM LOGISTICA LTDA | F12: COMPANHIA INDUSTRIAL DE CIMENTO APODI | G12: 11662.2
A13: 2026-01 | B13: 418 | C13: F G INTELIGENCIA EM LOGISTICA LTDA | F13: COMPANHIA INDUSTRIAL DE CIMENTO APODI | G13: 11798.6
A14: 2026-01 | B14: 409 | C14: F G INTELIGENCIA EM LOGISTICA LTDA | F14: COMPANHIA INDUSTRIAL DE CIMENTO APODI | G14: 11683.9
A15: 2026-01 | B15: 408 | C15: F G INTELIGENCIA EM LOGISTICA LTDA | F15: COMPANHIA INDUSTRIAL DE CIMENTO APODI | G15: 11776.9
A16: 2026-01 | B16: 407 | C16: F G INTELIGENCIA EM LOGISTICA LTDA | F16: COMPANHIA INDUSTRIAL DE CIMENTO APODI | G16: 2307.5
A17: 2026-01 | B17: 405 | C17: F G INTELIGENCIA EM LOGISTICA LTDA | F17: COMPANHIA INDUSTRIAL DE CIMENTO APODI | G17: 11711.8
A18: 2026-01 | B18: 401 | C18: F G INTELIGENCIA EM LOGISTICA LTDA | F18: COMPANHIA INDUSTRIAL DE CIMENTO APODI | G18: 11764.5
A19: 2026-01 | B19: 373 | C19: F G INTELIGENCIA EM LOGISTICA LTDA | F19: COMPANHIA INDUSTRIAL DE CIMENTO APODI | G19: 11795.5
... A31: 2026-01 | B31: 397 | C31: F G INTELIGENCIA EM LOGISTICA LTDA | F31: COMPANHIA INDUSTRIAL DE CIMENTO APODI | G31: 11699.4
A32: 2026-08 | B32: 839 | C32: F G INTELIGENCIA EM LOGISTICA LTDA | D32: Quixeré/CE | E32: Teresina/PI | F32: COMPANHIA INDUSTRIAL DE CIMENTO APODI | G32: 12566.4
A33: 2026-08 | B33: 842 | C33: F G INTELIGENCIA EM LOGISTICA LTDA | D33: Quixeré/CE | E33: Teresina/PI | F33: COMPANHIA INDUSTRIAL DE CIMENTO APODI | G33: 12437.7
A34: 2026-08 | B34: 845 | C34: F G INTELIGENCIA EM LOGISTICA LTDA | D34: Quixeré/CE | E34: Teresina/PI | F34: COMPANHIA INDUSTRIAL DE CIMENTO APODI | G34: 12530.1
F35: TOTAL | G35: =SUM(G4:G34)
